Workbook

Sheet Tổng hợp
A1: BÁO CÁO TIỀN THU VỀ TÀI KHOẢN THÁNG 7.2026/Collections received in July
A2: TÀI KHOẢN NHẬN Bank account | B2: THU HỘ KHÁCH WIFI CỐ ĐỊNH CỦA ĐẠI LÝ Collect fixed Wi-Fi payments from the agent’s customers | D2: WIFI CẦM TAY | H2: Other | I2: Chưa xác định/Not yet determined | J2: TỔNG/ TOTAL
B3: Cọc/ Deposit | C3: Cước/Monthly fee | D3: Khách sử dụng từ tháng 7 Customer has been using it since July. | F3: Khách sử dụng trước tháng 7 Customer used it before July
D4: Cọc/ Deposit | E4: Cước/ Monthly fee | F4: Cọc/ Deposit | G4: Cước/ Monthly fee
A5: GMO | B5: =SUMIFS(GMO!G:G,GMO!E:E,"Wifi cố định") -> 48451 | C5: =SUMIFS(GMO!H:H,GMO!E:E,"Wifi cố định") -> 540352
A6: Yucho Arai | B6: =SUMIFS('Yucho Arai'!H:H,'Yucho Arai'!F:F,"Cố định") -> 754789 | C6: =SUMIFS('Yucho Arai'!I:I,'Yucho Arai'!F:F,"Cố định") -> 15761
A7: SBI
A8: Arai 7121 | C8: =SUMIF('Arai 7121'!G:G,"cố định",'Arai 7121'!B:B) -> 123300
A9: TỔNG | B9: =SUM(B5:B8) -> 803240 | C9: =SUM(C5:C8) -> 679413
A10: Tiền cần trả cho đại lý | C10: =+C9 -> 679413

Sheet Tổng hợp tiền thu theo mã U
D1: STT | E1: ID | F1: CỌC | G1: CƯỚC | H1: TOTAL
F2: =SUBTOTAL(9,F3:F1000) -> 803240 | G2: =SUBTOTAL(9,G3:G1000) -> 679413 | H2: =SUBTOTAL(9,H3:H1000) -> 1482653
D3: 1 | E3: U00003129596 | F3: =SUMIF('Yucho Arai'!N:N,'Tổng hợp tiền thu theo mã U'!E3,'Yucho Arai'!H:H)+SUMIF(GMO!I:I,'Tổng hợp tiền thu theo mã U'!E3,GMO!G:G) -> 6850 | G3: =SUMIF('Yucho Arai'!N:N,'Tổng hợp tiền thu theo mã U'!E3,'Yucho Arai'!I:I)+SUMIF(GMO!I:I,'Tổng hợp tiền thu theo mã U'!E3,GMO!H:H)+SUMIF('Arai 7121'!H:H,'Tổng hợp tiền thu theo mã U'!E3,'Arai 7121'!B:B) -> 0 | H3: =G3+F3 -> 6850
D4: 2 | E4: U00007891899 | F4: =SUMIF('Yucho Arai'!N:N,'Tổng hợp tiền thu theo mã U'!E4,'Yucho Arai'!H:H)+SUMIF(GMO!I:I,'Tổng hợp tiền thu theo mã U'!E4,GMO!G:G) -> 6850 | G4: =SUMIF('Yucho Arai'!N:N,'Tổng hợp tiền thu theo mã U'!E4,'Yucho Arai'!I:I)+SUMIF(GMO!I:I,'Tổng hợp tiền thu theo mã U'!E4,GMO!H:H)+SUMIF('Arai 7121'!H:H,'Tổng hợp tiền thu theo mã U'!E4,'Arai 7121'!B:B) -> 0 | H4: =G4+F4 -> 6850
D5: 3 | E5: U00003130103 | F5: =SUMIF('Yucho Arai'!N:N,'Tổng hợp tiền thu theo mã U'!E5,'Yucho Arai'!H:H)+SUMIF(GMO!I:I,'Tổng hợp tiền thu theo mã U'!E5,GMO!G:G) -> 4290 | G5: =SUMIF('Yucho Arai'!N:N,'Tổng hợp tiền thu theo mã U'!E5,'Yucho Arai'!I:I)+SUMIF(GMO!I:I,'Tổng hợp tiền thu theo mã U'!E5,GMO!H:H)+SUMIF('Arai 7121'!H:H,'Tổng hợp tiền thu theo mã U'!E5,'Arai 7121'!B:B) -> 0 | H5: =G5+F5 -> 4290
D6: 4 | E6: U00007882257 | F6: =SUMIF('Yucho Arai'!N:N,'Tổng hợp tiền thu theo mã U'!E6,'Yucho Arai'!H:H)+SUMIF(GMO!I:I,'Tổng hợp tiền thu theo mã U'!E6,GMO!G:G) -> 4297 | G6: =SUMIF('Yucho Arai'!N:N,'Tổng hợp tiền thu theo mã U'!E6,'Yucho Arai'!I:I)+SUMIF(GMO!I:I,'Tổng hợp tiền thu theo mã U'!E6,GMO!H:H)+SUMIF('Arai 7121'!H:H,'Tổng hợp tiền thu theo mã U'!E6,'Arai 7121'!B:B) -> 0 | H6: =G6+F6 -> 4297
D7: 5 | E7: U00007885485 | F7: =SUMIF('Yucho Arai'!N:N,'Tổng hợp tiền thu theo mã U'!E7,'Yucho Arai'!H:H)+SUMIF(GMO!I:I,'Tổng hợp tiền thu theo mã U'!E7,GMO!G:G) -> 3297 | G7: =SUMIF('Yucho Arai'!N:N,'Tổng hợp tiền thu theo mã U'!E7,'Yucho Arai'!I:I)+SUMIF(GMO!I:I,'Tổng hợp tiền thu theo mã U'!E7,GMO!H:H)+SUMIF('Arai 7121'!H:H,'Tổng hợp tiền thu theo mã U'!E7,'Arai 7121'!B:B) -> 0 | H7: =G7+F7 -> 3297
D8: 6 | E8: U00003130098 | F8: =SUMIF('Yucho Arai'!N:N,'Tổng hợp tiền thu theo mã U'!E8,'Yucho Arai'!H:H)+SUMIF(GMO!I:I,'Tổng hợp tiền thu theo mã U'!E8,GMO!G:G) -> 3000 | G8: =SUMIF('Yucho Arai'!N:N,'Tổng hợp tiền thu theo mã U'!E8,'Yucho Arai'!I:I)+SUMIF(GMO!I:I,'Tổng hợp tiền thu theo mã U'!E8,GMO!H:H)+SUMIF('Arai 7121'!H:H,'Tổng hợp tiền thu theo mã U'!E8,'Arai 7121'!B:B) -> 297 | H8: =G8+F8 -> 3297
D9: 7 | E9: U00007884021 | F9: =SUMIF('Yucho Arai'!N:N,'Tổng hợp tiền thu theo mã U'!E9,'Yucho Arai'!H:H)+SUMIF(GMO!I:I,'Tổng hợp tiền thu theo mã U'!E9,GMO!G:G) -> 4000 | G9: =SUMIF('Yucho Arai'!N:N,'Tổng hợp tiền thu theo mã U'!E9,'Yucho Arai'!I:I)+SUMIF(GMO!I:I,'Tổng hợp tiền thu theo mã U'!E9,GMO!H:H)+SUMIF('Arai 7121'!H:H,'Tổng hợp tiền thu theo mã U'!E9,'Arai 7121'!B:B) -> 290 | H9: =G9+F9 -> 4290
D10: 8 | E10: U00007885523 | F10: =SUMIF('Yucho Arai'!N:N,'Tổng hợp tiền thu theo mã U'!E10,'Yucho Arai'!H:H)+SUMIF(GMO!I:I,'Tổng hợp tiền thu theo mã U'!E10,GMO!G:G) -> 2797 | G10: =SUMIF('Yucho Arai'!N:N,'Tổng hợp tiền thu theo mã U'!E10,'Yucho Arai'!I:I)+SUMIF(GMO!I:I,'Tổng hợp tiền thu theo mã U'!E10,GMO!H:H)+SUMIF('Arai 7121'!H:H,'Tổng hợp tiền thu theo mã U'!E10,'Arai 7121'!B:B) -> 0 | H10: =G10+F10 -> 2797
D11: 9 | E11: U00007872681 | F11: =SUMIF('Yucho Arai'!N:N,'Tổng hợp tiền thu theo mã U'!E11,'Yucho Arai'!H:H)+SUMIF(GMO!I:I,'Tổng hợp tiền thu theo mã U'!E11,GMO!G:G) -> 3000 | G11: =SUMIF('Yucho Arai'!N:N,'Tổng hợp tiền thu theo mã U'!E11,'Yucho Arai'!I:I)+SUMIF(GMO!I:I,'Tổng hợp tiền thu theo mã U'!E11,GMO!H:H)+SUMIF('Arai 7121'!H:H,'Tổng hợp tiền thu theo mã U'!E11,'Arai 7121'!B:B) -> 290 | H11: =G11+F11 -> 3290
D12: 10 | E12: U00007885536 | F12: =SUMIF('Yucho Arai'!N:N,'Tổng hợp tiền thu theo mã U'!E12,'Yucho Arai'!H:H)+SUMIF(GMO!I:I,'Tổng hợp tiền thu theo mã U'!E12,GMO!G:G) -> 3297 | G12: =SUMIF('Yucho Arai'!N:N,'Tổng hợp tiền thu theo mã U'!E12,'Yucho Arai'!I:I)+SUMIF(GMO!I:I,'Tổng hợp tiền thu theo mã U'!E12,GMO!H:H)+SUMIF('Arai 7121'!H:H,'Tổng hợp tiền thu theo mã U'!E12,'Arai 7121'!B:B) -> 0 | H12: =G12+F12 -> 3297
D13: 11 | E13: U00003130101 | F13: =SUMIF('Yucho Arai'!N:N,'Tổng hợp tiền thu theo mã U'!E13,'Yucho Arai'!H:H)+SUMIF(GMO!I:I,'Tổng hợp tiền thu theo mã U'!E13,GMO!G:G) -> 3297 | G13: =SUMIF('Yucho Arai'!N:N,'Tổng hợp tiền thu theo mã U'!E13,'Yucho Arai'!I:I)+SUMIF(GMO!I:I,'Tổng hợp tiền thu theo mã U'!E13,GMO!H:H)+SUMIF('Arai 7121'!H:H,'Tổng hợp tiền thu theo mã U'!E13,'Arai 7121'!B:B) -> 0 | H13: =G13+F13 -> 3297
D14: 12 | E14: U00007885516 | F14: =SUMIF('Yucho Arai'!N:N,'Tổng hợp tiền thu theo mã U'!E14,'Yucho Arai'!H:H)+SUMIF(GMO!I:I,'Tổng hợp tiền thu theo mã U'!E14,GMO!G:G) -> 6594 | G14: =SUMIF('Yucho Arai'!N:N,'Tổng hợp tiền thu theo mã U'!E14,'Yucho Arai'!I:I)+SUMIF(GMO!I:I,'Tổng hợp tiền thu theo mã U'!E14,GMO!H:H)+SUMIF('Arai 7121'!H:H,'Tổng hợp tiền thu theo mã U'!E14,'Arai 7121'!B:B) -> 0 | H14: =G14+F14 -> 6594
... D465: 462 | E465: U00007883086 | F465: =SUMIF('Yucho Arai'!N:N,'Tổng hợp tiền thu theo mã U'!E465,'Yucho Arai'!H:H)+SUMIF(GMO!I:I,'Tổng hợp tiền thu theo mã U'!E465,GMO!G:G) -> 0 | G465: =SUMIF('Yucho Arai'!N:N,'Tổng hợp tiền thu theo mã U'!E465,'Yucho Arai'!I:I)+SUMIF(GMO!I:I,'Tổng hợp tiền thu theo mã U'!E465,GMO!H:H)+SUMIF('Arai 7121'!H:H,'Tổng hợp tiền thu theo mã U'!E465,'Arai 7121'!B:B) -> 5000 | H465: =G465+F465 -> 5000

Sheet Báo cáo cọc
A1: BÁO CÁO TIỀN CỌC HẾT THÁNG 8 | H1: NOTE
A2: 1 | B2: Tiền cọc tính đến hết tháng 6 | C2: Total customer deposit balance as of the end of January | E2: 5677256
A3: 2 | B3: Doanh thu tháng 7 | C3: Total sales received in February, broken down by account (Yucho / SBI / GMO) | D3: Yucho | E3: ='Tổng hợp'!G6 -> 0
D4: SBI | E4: ='Tổng hợp'!G7 -> 0
D5: GMO | E5: ='Tổng hợp'!G5 -> 0
A6: 3 | B6: Cọc tháng 7 | C6: Total customer deposits collected in February, broken down by account (Yucho / SBI / GMO) | D6: Yucho | E6: ='Tổng hợp'!B6+'Tổng hợp'!D6+'Tổng hợp'!F6 -> 754789
D7: SBI
D8: GMO | E8: ='Tổng hợp'!B5+'Tổng hợp'!D5+'Tổng hợp'!F5 -> 48451
A9: 4 | B9: Tiền hoàn cọc tháng 7 | C9: Total customer deposit refunds made in February
A10: 5 | B10: Tiền cọc chuyển thành doanh thu trong tháng 7 | C10: Total amount of previously held customer deposits that were recognized as sales during February
A11: 6 | B11: Tiền cọc tính đến hết tháng 7 | C11: Total customer deposit balance as of the end of February | E11: =E2+E6-E9-E10+E8 -> 6480496
A12: 7 | B12: Các phần khác về thu tiền | C12: Any other notable items regarding sales receipts or refunds | D12: Yucho | E12: ='Tổng hợp'!I6+'Tổng hợp'!H6+'Tổng hợp'!E6+'Tổng hợp'!C6 -> 15761 | H12: Gồm các khoản khác và không rõ, tiền cước của các khách mới từ tháng 7+8
D13: SBI | E13: ='Tổng hợp'!H7 -> 0 | H13: Gồm các khoản luân chuyển, Hoa hồng Sonet, phí vận chuyển được hoàn về
D14: GMO | E14: ='Tổng hợp'!I5+'Tổng hợp'!H5+'Tổng hợp'!E5+'Tổng hợp'!C5 -> 540352 | H14: Tiền wifi cố định đại lý chuyển nhờ

Sheet Yucho Arai
A1: ĐƠN VỊ | B1: NGÀY THÁNG | C1: MÃ KHÁCH HÀNG | D1: TÊN KHÁCH HÀNG | F1: LOẠI DỊCH VỤ | G1: THU | H1: CỌC | I1: CƯỚC | J1: KHÁC/KHÔNG RÕ | K1: CHI | N1: Mã U (NTT)
G2: =SUBTOTAL(9,G3:G10000) -> 770550 | H2: =SUBTOTAL(9,H3:H10000) -> 754789 | I2: =SUBTOTAL(9,I3:I10000) -> 15761 | J2: =SUBTOTAL(9,J3:J10000) -> 0 | K2: =SUBTOTAL(9,K3:K10000) -> 0
A3: ĐLý tecno | B3: 46235 | C3: KH02322 | D3: Đại lý Kiên- Luân JP | F3: Cố định | G3: 6850 | H3: 6850 | I3: 0 | J3: 0 | M3: Đơn mới | N3: U00003129596 | O3: 20260801 | P3: 202608010000001 | Q3: 6850 | S3: 送金 | T3: ＮＧＵＹＥＮ Ｖ | U3: 241.647
A4: Công ty | B4: 46235 | C4: KH01097 | D4: Hoàng Sơn | F4: Cầm tay | G4: 7700 | I4: 7700 | J4: 0 | M4: Khách cũ | O4: 20260801 | P4: 202608010000002 | Q4: 7700 | S4: 送金 | T4: ＤＵＯＮＧ ＶＡ | U4: 249.347
A5: ĐLý tecno | B5: 46235 | C5: KH02600 | D5: Đại lý AKIKO | F5: Cố định | G5: 6850 | H5: 6850 | I5: 0 | J5: 0 | M5: Đơn mới | N5: U00007891899 | O5: 20260801 | P5: 202608010000003 | Q5: 6850 | S5: 送金 | T5: ＴＨＡＣＨ ＴＨ | U5: 256.197
A6: Công ty | B6: 46235 | C6: KH01155 | D6: Thu Cúc | F6: Cầm tay | G6: 2475 | I6: 2475 | J6: 0 | M6: Khách cũ | O6: 20260801 | P6: 202608010000004 | Q6: 2475 | S6: 送金 | T6: ＴＲＡＮ ＴＨＩ | U6: 258.672
A7: Công ty | B7: 46235 | C7: KH01145 | D7: Hoangtrung Nguyen | F7: Cầm tay | G7: 3850 | I7: 3850 | J7: 0 | M7: Khách cũ | O7: 20260801 | P7: 202608010000005 | Q7: 3850 | S7: 送金 | T7: ＮＧＵＹＥＮ Ｓ | U7: 262.522
A8: ĐLý Hoàng | B8: 46235 | C8: KH03517 | D8: Takahashi Maricel Hallig | F8: Cố định | G8: 493 | H8: 493 | I8: 0 | J8: 0 | M8: Đơn mới | N8: U00003130103 | O8: 20260801 | P8: 202608010000006 | Q8: 493 | S8: 送金 | T8: ＴＡＫＡＨＡＳＨ | U8: 263.015
A9: ĐLý Hoàng | B9: 46235 | C9: KH00498 | D9: Đỗ Phong | F9: Cầm tay | G9: 500 | H9: 500 | I9: 0 | J9: 0 | M9: Đơn mới | O9: 20260801 | P9: 202608010000007 | Q9: 500 | S9: 送金 | T9: ＬＥ ＴＨＩ Ｓ | U9: 263.515
A10: ĐLý Việt | B10: 46236 | C10: KH03511 | D10: Osep Rosete | F10: Cố định | G10: 500 | H10: 500 | I10: 0 | J10: 0 | M10: Đơn mới | N10: U00007882257 | O10: 20260802 | P10: 202608020000001 | Q10: 500 | S10: 送金 | T10: ＳＡＮＣＨＥＺ | U10: 264.015
A11: Công ty | B11: 46236 | C11: KH02748 | D11: Pyaephyo Kyaw | F11: Cầm tay | G11: 3850 | I11: 3850 | J11: 0 | M11: Khách cũ | O11: 20260802 | P11: 202608020000002 | Q11: 3850 | S11: 送金 | T11: ＰＹＡＥ ＰＨＹ | U11: 267.865
A12: Công ty | B12: 46236 | C12: KH00926 | D12: Nhung Min's | F12: Cầm tay | G12: 46200 | I12: 46200 | J12: 0 | M12: Khách cũ | O12: 20260802 | P12: 202608020000003 | Q12: 46200 | S12: 送金 | T12: ＬＵＯＮＧ ＶＡ | U12: 314.065
A13: ĐLý Hoàng | B13: 46237 | C13: KH03356 | D13: Kewal Ghimire | F13: Cầm tay | G13: 6647 | H13: 3000 | I13: 3647 | J13: 0 | M13: Đơn mới | O13: 20260803 | P13: 202608030000001 | Q13: 6647 | S13: 送金 | T13: 81961912863ﾆﾂ | U13: 320.712
A14: ĐLý Hoàng | B14: 46237 | C14: KH03366 | D14: オランデ ラケル | F14: Cố định | G14: 4290 | H14: 4000 | I14: 290 | J14: 0 | M14: Đơn mới | N14: U00007889069 | O14: 20260803 | P14: 202608030000002 | Q14: 4290 | S14: 送金 | T14: 81961912631ﾆﾂ | U14: 325.002
A15: ĐLý Việt | B15: 46237 | C15: KH03440 | D15: Dreads Shevo | F15: Cố định | G15: 3297 | H15: 3000 | I15: 297 | J15: 0 | M15: Đơn mới | N15: U00003130098 | O15: 20260803 | P15: 202608030000003 | Q15: 3297 | S15: 送金 | T15: 81961912955ﾆﾂ | U15: 328.299
A16: ĐLý Hoàng | B16: 46237 | C16: KH03367 | D16: Mamoouroii Diouf | F16: Cố định | G16: 4290 | H16: 4000 | I16: 290 | J16: 0 | M16: Đơn mới | N16: U00007884021 | O16: 20260803 | P16: 202608030000004 | Q16: 4290 | S16: 送金 | T16: 81961912642ﾆﾂ | U16: 332.589
A17: ĐLý Hoàng | B17: 46237 | C17: KH03411 | D17: Shima Jorge | F17: Cầm tay | G17: 7140 | H17: 3000 | I17: 4140 | J17: 0 | M17: Đơn mới | O17: 20260803 | P17: 202608030000005 | Q17: 7140 | S17: 送金 | T17: 81961912885ﾆﾂ | U17: 339.729
A18: ĐLý Hoàng | B18: 46237 | C18: KH03392 | D18: Junglen Villanueva | F18: Cầm tay | G18: 8290 | H18: 4000 | I18: 4290 | J18: 0 | M18: Đơn mới | O18: 20260803 | P18: 202608030000006 | Q18: 8290 | S18: 送金 | T18: 81961912701ﾆﾂ | U18: 348.019
A19: ĐLý Việt | B19: 46237 | C19: KH03446 | D19: Ferndo Acero | F19: Cầm tay | G19: 6597 | H19: 4000 | I19: 2597 | J19: 0 | M19: Đơn mới | O19: 20260803 | P19: 202608030000007 | Q19: 6597 | S19: 送金 | T19: 81961912826ﾆﾂ | U19: 354.616
A20: ĐLý Hoàng | B20: 46237 | C20: KH03469 | D20: Ly Chinh | F20: Cầm tay | G20: 7092 | H20: 4000 | I20: 3092 | J20: 0 | M20: Đơn mới | O20: 20260803 | P20: 202608030000008 | Q20: 7092 | S20: 送金 | T20: 81961912900ﾆﾂ | U20: 361.708
A21: ĐLý Việt | B21: 46237 | C21: KH03451 | D21: Dang Vizcarra- de Leon | F21: Cố định | G21: 2797 | H21: 2797 | I21: 0 | J21: 0 | M21: Đơn mới | N21: U00007885523 | O21: 20260803 | P21: 202608030000009 | Q21: 2797 | S21: 送金 | T21: 81961912981ﾆﾂ | U21: 364.505
A22: ĐLý Hoàng | B22: 46237 | C22: KH03430 | D22: Whitney Guimare | F22: Cầm tay | G22: 7140 | H22: 3000 | I22: 4140 | J22: 0 | M22: Đơn mới | O22: 20260803 | P22: 202608030000010 | Q22: 7140 | S22: 送金 | T22: 81961912771ﾆﾂ | U22: 371.645
A23: ĐLý Việt | B23: 46237 | C23: KH03416 | D23: Eduardo Fujiki | F23: Cố định | G23: 3290 | H23: 3000 | I23: 290 | J23: 0 | M23: Đơn mới | N23: U00007872681 | O23: 20260803 | P23: 202608030000011 | Q23: 3290 | S23: 送金 | T23: 81961912911ﾆﾂ | U23: 374.935
A24: ĐLý Hoàng | B24: 46237 | C24: KH03490 | D24: Rosalie Castalone | F24: Cầm tay | G24: 6090 | H24: 3000 | I24: 3090 | J24: 0 | M24: Đơn mới | O24: 20260803 | P24: 202608030000012 | Q24: 6090 | S24: 送金 | T24: 81961913191ﾆﾂ | U24: 381.025
A25: ĐLý Việt | B25: 46237 | C25: KH03458 | D25: Ar Kar | F25: Cố định | G25: 3297 | H25: 3297 | I25: 0 | J25: 0 | M25: Đơn mới | N25: U00007885485 | O25: 20260803 | P25: 202608030000013 | Q25: 3297 | S25: 送金 | T25: 81961912944ﾆﾂ | U25: 384.322
A26: ĐLý Hoàng | B26: 46237 | C26: KH03381 | D26: Michelle Mekz | F26: Cố định | G26: 4290 | H26: 4000 | I26: 290 | J26: 0 | M26: Đơn mới | N26: U00007892020 | O26: 20260803 | P26: 202608030000014 | Q26: 4290 | S26: 送金 | T26: 81961913062ﾆﾂ | U26: 388.612
A27: ĐLý Việt | B27: 46237 | C27: KH03397 | D27: Dumindu J Rajapaksha | F27: Cố định | G27: 3297 | H27: 3297 | I27: 0 | J27: 0 | M27: Đơn mới | N27: U00003130101 | O27: 20260803 | P27: 202608030000015 | Q27: 3297 | S27: 送金 | T27: 81961912966ﾆﾂ | U27: 391.909
A28: ĐLý Việt | B28: 46237 | C28: KH03473 | D28: Juka Sasaki | F28: Cố định | G28: 3297 | H28: 3297 | I28: 0 | J28: 0 | M28: Đơn mới | N28: U00007885516 | O28: 20260803 | P28: 202608030000016 | Q28: 3297 | S28: 送金 | T28: 81961913003ﾆﾂ | U28: 395.206
A29: ĐLý Hoàng | B29: 46237 | C29: KH03485 | D29: Muhammed Sahal | F29: Cầm tay | G29: 5250 | H29: 3000 | I29: 2250 | J29: 0 | M29: Đơn mới | O29: 20260803 | P29: 202608030000017 | Q29: 5250 | S29: 送金 | T29: 81961913036ﾆﾂ | U29: 400.456
A30: ĐLý Hoàng | B30: 46237 | C30: KH03449 | D30: Vandam Sato | F30: Cầm tay | G30: 8290 | H30: 4000 | I30: 4290 | J30: 0 | M30: Đơn mới | O30: 20260803 | P30: 202608030000018 | Q30: 8290 | S30: 送金 | T30: 81961912815ﾆﾂ | U30: 408.746
A31: ĐLý tecno | B31: 46237 | C31: KH02600 | D31: Đại lý AKIKO | F31: Cố định | G31: 6850 | H31: 6850 | I31: 0 | J31: 0 | M31: Đơn mới | N31: U00007892018 | O31: 20260803 | P31: 202608030000019 | Q31: 6850 | S31: 送金 | T31: ＴＲＩＮＨ ＤＡ | U31: 415.596
A32: ĐLý Việt | B32: 46237 | C32: KH03525 | D32: Kaung Myat San | F32: Cầm tay | G32: 493 | H32: 493 | I32: 0 | J32: 0 | M32: Đơn mới | O32: 20260803 | P32: 202608030000020 | Q32: 493 | S32: ことら | T32: ｶｳﾝ ﾐﾔﾂ ｻﾝ | U32: 416.089
A33: ĐLý Hoàng | B33: 46237 | C33: KH03533 | D33: Phạm Bá Manh | F33: Cố định | G33: 4000 | H33: 4000 | I33: 0 | J33: 0 | M33: Đơn mới | N33: U00007883738 | O33: 20260803 | P33: 202608030000021 | Q33: 4000 | S33: 送金 | T33: ＰＨＡＭ ＢＡ | U33: 420.089
A34: Công ty | B34: 46237 | C34: KH01456 | D34: Trần Thị Đào | F34: Cầm tay | G34: 3850 | I34: 3850 | J34: 0 | M34: Khách cũ | O34: 20260803 | P34: 202608030000022 | Q34: 3850 | S34: 送金 | T34: ＴＲＡＮ ＴＨＩ | U34: 423.939
A35: ĐLý tecno | B35: 46237 | C35: KH02600 | D35: Đại lý AKIKO | F35: Cố định | G35: 6850 | H35: 6850 | I35: 0 | J35: 0 | M35: Đơn mới | N35: U00007891917 | O35: 20260803 | P35: 202608030000023 | Q35: 6850 | S35: 送金 | T35: ＮＧＵＹＥＮ Ｔ | U35: 430.789
A36: đại lý Hoa | B36: 46237 | C36: KH00419 | D36: Nguyễn Chi | F36: Cầm tay | G36: 2153 | I36: 2153 | J36: 0 | M36: Đơn mới | O36: 20260803 | P36: 202608030000024 | Q36: 2153 | S36: 送金 | T36: ＮＧＵＹＥＮ Ｔ | U36: 432.942
A37: ĐLý tecno | B37: 46237 | C37: KH02271 | D37: Đại Lý Kiên- Sơn Tùng | F37: Cố định | G37: 7000 | H37: 7000 | I37: 0 | J37: 0 | M37: Đơn mới | N37: U00007889274 | O37: 20260803 | P37: 202608030000025 | Q37: 7000 | S37: 送金 | T37: ＮＧＵＹＥＮ Ｖ | U37: 439.942
A38: ĐLý Hoàng | B38: 46238 | C38: KH03379 | D38: Mab Aguilar Betz | F38: Cầm tay | G38: 5985 | H38: 3000 | I38: 2985 | J38: 0 | M38: Đơn mới | O38: 20260804 | P38: 202608040000001 | Q38: 5985 | S38: 送金 | T38: 81961913025ﾆﾂ | U38: 445.927
A39: ĐLý Hoàng | B39: 46238 | C39: KH02378 | D39: Avenilda Liwacat | F39: Cầm tay | G39: 5252 | H39: 3000 | I39: 2252 | J39: 0 | M39: Đơn mới | O39: 20260804 | P39: 202608040000002 | Q39: 5252 | S39: 送金 | T39: 81961912896ﾆﾂ | U39: 451.179
A40: ĐLý Việt | B40: 46238 | C40: KH03482 | D40: Nang Hsi Ying | F40: Cầm tay | G40: 5252 | H40: 3000 | I40: 2252 | J40: 0 | M40: Đơn mới | O40: 20260804 | P40: 202608040000003 | Q40: 5252 | S40: 送金 | T40: 81961913073ﾆﾂ | U40: 456.431
A41: Công ty | B41: 46238 | C41: KH00708 | D41: Lài Lê | F41: Cầm tay | G41: 3850 | I41: 3850 | J41: 0 | M41: Khách cũ | O41: 20260804 | P41: 202608040000004 | Q41: 6650 | S41: 送金 | T41: ＬＥ ＴＨＩ Ｋ | U41: 463.081
A42: Công ty | B42: 46238 | C42: KH00708 | D42: Lài Lê | F42: Cầm tay | G42: 2800 | I42: 2800 | J42: 0 | M42: Khách cũ
A43: ĐLý Việt | B43: 46238 | C43: KH03557 | D43: Mekasu Prajapati | F43: Cố định | G43: 500 | H43: 500 | I43: 0 | J43: 0 | M43: Đơn mới | N43: U00003130090 | O43: 20260804 | P43: 202608040000005 | Q43: 500 | S43: ことら | T43: ﾊﾟﾗｼﾞﾔﾊﾟﾃｲ ﾑｹ | U43: 463.581
A44: ĐLý Việt | B44: 46238 | C44: KH03535 | D44: Kent Tũm | F44: Cố định | G44: 3000 | H44: 3000 | I44: 0 | J44: 0 | M44: Đơn mới | N44: U00007891196 | O44: 20260804 | P44: 202608040000006 | Q44: 3000 | S44: 送金 | T44: ＮＧＵＹＥＮ Ｘ | U44: 466.581
A45: Công ty | B45: 46238 | C45: #N/A | F45: Cố định | G45: 2000 | I45: 2000 | J45: 0 | M45: Khách cũ | N45: U00007854447 | O45: 20260804 | P45: 202608040000007 | Q45: 2000 | S45: 送金 | T45: ＶＵ ＴＵＮＧ | U45: 468.581
A46: ĐLý Hoàng | B46: 46239 | C46: KH03501 | D46: An Minh | F46: Cầm tay | G46: 5987 | H46: 3000 | I46: 2987 | J46: 0 | M46: Đơn mới | O46: 20260805 | P46: 202608050000001 | Q46: 5987 | S46: 送金 | T46: 81961912255ﾆﾂ | U46: 474.568
A47: ĐLý Việt | B47: 46239 | C47: KH03457 | D47: Samjhana Karki | F47: Cố định | G47: 3297 | H47: 3000 | I47: 297 | J47: 0 | M47: Đơn mới | N47: U00003130096 | O47: 20260805 | P47: 202608050000002 | Q47: 3297 | S47: 送金 | T47: 81961912970ﾆﾂ | U47: 477.865
A48: ĐLý Việt | B48: 46239 | C48: KH03465 | D48: ファビアン バロン | F48: Cầm tay | G48: 7797 | H48: 4000 | I48: 3797 | J48: 0 | M48: Đơn mới | O48: 20260805 | P48: 202608050000003 | Q48: 7797 | S48: 送金 | T48: 81961913040ﾆﾂ | U48: 485.662
A49: ĐLý tecno | B49: 46239 | C49: KH03476 | D49: Oliver Manalo | F49: Cầm tay | G49: 5250 | H49: 3000 | I49: 2250 | J49: 0 | M49: Đơn mới | O49: 20260805 | P49: 202608050000004 | Q49: 5250 | S49: 送金 | T49: 81961912992ﾆﾂ | U49: 490.912
A50: ĐLý Việt | B50: 46239 | C50: KH03460 | D50: シェイン ゴンザレス | F50: Cố định | G50: 3297 | H50: 3000 | I50: 297 | J50: 0 | M50: Đơn mới | N50: U00007884526 | O50: 20260805 | P50: 202608050000005 | Q50: 3297 | S50: 送金 | T50: 81961913051ﾆﾂ | U50: 494.209
A51: ĐLý Hoàng | B51: 46239 | C51: KH03529 | D51: Yuri | F51: Cầm tay | G51: 5250 | H51: 3000 | I51: 2250 | J51: 0 | M51: Đơn mới | O51: 20260805 | P51: 202608050000006 | Q51: 5250 | S51: 送金 | T51: 81961910531ﾆﾂ | U51: 499.459
A52: ĐLý Việt | B52: 46239 | C52: KH03504 | D52: Sandra Liliana Hernández | F52: Cầm tay | G52: 6597 | H52: 4000 | I52: 2597 | J52: 0 | M52: Đơn mới | O52: 20260805 | P52: 202608050000007 | Q52: 6597 | S52: 送金 | T52: 81961913143ﾆﾂ | U52: 506.056
A53: ĐLý Việt | B53: 46239 | C53: KH03515 | D53: MāhéñDrā Ràjpøøt | F53: Cố định | G53: 3292 | H53: 3000 | I53: 292 | J53: 0 | M53: Đơn mới | N53: U00007885689 | O53: 20260805 | P53: 202608050000008 | Q53: 3292 | S53: 送金 | T53: 81961913095ﾆﾂ | U53: 509.348
A54: ĐLý tecno | B54: 46239 | C54: KH02600 | D54: Đại lý AKIKO | F54: Cố định | G54: 6850 | H54: 6850 | I54: 0 | J54: 0 | M54: Đơn mới | N54: U00007891921 | O54: 20260805 | P54: 202608050000009 | Q54: 6850 | S54: 送金 | T54: ＴＲＡＮ ＭＩＮ | U54: 516.198
A55: ĐLý Hoàng | B55: 46239 | C55: KH03578 | D55: Nt Oanh | F55: Cố định | G55: 4000 | H55: 4000 | I55: 0 | J55: 0 | M55: Đơn mới | N55: U00007895361 | O55: 20260805 | P55: 202608050000010 | Q55: 4000 | S55: 送金 | T55: ＮＧＵＹＥＮ Ｔ | U55: 520.198
A56: Công ty | B56: 46239 | C56: KH00249 | D56: TÀi S | F56: Cầm tay | G56: 2475 | I56: 2475 | J56: 0 | M56: Khách cũ | O56: 20260805 | P56: 202608050000011 | Q56: 2475 | S56: 送金 | T56: ＴＲＡＮ ＴＩＥ | U56: 522.673
A57: Công ty | B57: 46239 | C57: KH00208 | D57: Đỗ Hảo | F57: Cầm tay | G57: 2915 | I57: 2915 | J57: 0 | M57: Khách cũ | O57: 20260805 | P57: 202608050000012 | Q57: 2915 | S57: 送金 | T57: ＤＯ ＴＨＩＥＮ | U57: 525.588
A58: ĐLý Việt | B58: 46239 | C58: KH03557 | D58: Mekasu Prajapati | F58: Cố định | G58: 500 | H58: 500 | I58: 0 | J58: 0 | M58: Đơn mới | N58: U00003130090 | O58: 20260805 | P58: 202608050000013 | Q58: 500 | S58: 送金 | T58: ｱﾗｲ ﾀｶｱｷ | U58: 526.088
A59: Công ty | B59: 46239 | C59: KH01260 | D59: Sơn Thack | F59: Cầm tay | G59: 2915 | I59: 2915 | J59: 0 | M59: Khách cũ | O59: 20260805 | P59: 202608050000014 | Q59: 2915 | S59: 送金 | T59: ＨＡ ＳＯＮ Ｔ | U59: 529.003
A60: Công ty | B60: 46239 | C60: KH00575 | D60: Thu Thảo | F60: Cầm tay | G60: 2915 | I60: 2915 | J60: 0 | M60: Khách cũ | O60: 20260805 | P60: 202608050000015 | Q60: 2915 | S60: 送金 | T60: ＬＥ ＴＨＩ Ｃ | U60: 531.918
A61: Công ty | B61: 46239 | C61: KH00807 | D61: Quốc Việt | F61: Cầm tay | G61: 5830 | I61: 5830 | J61: 0 | M61: Khách cũ | O61: 20260805 | P61: 202608050000016 | Q61: 5830 | S61: 送金 | T61: ＴＲＡＮ ＱＵＯ | U61: 537.748
A62: Công ty | B62: 46239 | C62: KH00570 | D62: Nguyễn Sang | F62: Cầm tay | G62: 2475 | I62: 2475 | J62: 0 | M62: Khách cũ | O62: 20260805 | P62: 202608050000017 | Q62: 2475 | S62: 送金 | T62: ＴＲＡＮ ＴＨＩ | U62: 540.223
A63: Công ty | B63: 46239 | C63: KH00262 | D63: Lê Văn Sơn | F63: Cầm tay | G63: 2915 | I63: 2915 | J63: 0 | M63: Khách cũ | O63: 20260805 | P63: 202608050000018 | Q63: 2915 | S63: 送金 | T63: ＬＥ ＶＡＮ Ｓ | U63: 543.138
A64: Công ty | B64: 46239 | C64: KH02962 | D64: Sa Su Ke | F64: Cầm tay | G64: 5600 | I64: 5600 | J64: 0 | M64: Khách cũ | O64: 20260805 | P64: 202608050000019 | Q64: 5600 | S64: 振込 | T64: ﾀﾞﾝ ｺﾝｱﾝ | U64: 548.738
A65: Công ty | B65: 46239 | C65: KH00622 | D65: CTV Nguyễn Thu | F65: Cầm tay | G65: 2475 | I65: 2475 | J65: 0 | M65: Khách cũ | O65: 20260805 | P65: 202608050000020 | Q65: 2475 | S65: 送金 | T65: ＤＡＮＧ ＴＨＩ | U65: 551.213
A66: Công ty | B66: 46239 | C66: KH01275 | D66: Văn Sỹ | F66: Cầm tay | G66: 2915 | I66: 2915 | J66: 0 | M66: Khách cũ | O66: 20260805 | P66: 202608050000021 | Q66: 2915 | S66: 送金 | T66: ＨＡ ＶＡＮ Ｓ | U66: 554.128
A67: ĐLý tecno | B67: 46239 | C67: KH02271 | D67: Đại Lý Kiên- Sơn Tùng | F67: Cố định | G67: 14000 | H67: 14000 | I67: 0 | J67: 0 | M67: Đơn mới | N67: U00007890671 | O67: 20260805 | P67: 202608050000022 | Q67: 14000 | S67: 送金 | T67: ＮＧＵＹＥＮ Ｔ | U67: 568.128
A68: Công ty | B68: 46240 | C68: KH01355 | D68: Naili Arifiyah | F68: Cầm tay | G68: 2915 | I68: 2915 | J68: 0 | M68: Khách cũ | O68: 20260806 | P68: 202608060000001 | Q68: 2915 | S68: 送金 | T68: ＮＡＩＬＩ ＡＲ | U68: 571.043
A69: Công ty | B69: 46240 | C69: KH01103 | D69: Nguyễn Thị Xuân | F69: Cầm tay | G69: 2475 | I69: 2475 | J69: 0 | M69: Khách cũ | O69: 20260806 | P69: 202608060000002 | Q69: 2475 | S69: 送金 | T69: ＮＧＵＹＥＮ Ｔ | U69: 573.518
A70: ĐLý Việt | B70: 46240 | C70: KH03566 | D70: Joan Santos | F70: Cố định | G70: 493 | I70: 493 | J70: 0 | M70: Đơn mới | N70: U00007884593 | O70: 20260806 | P70: 202608060000003 | Q70: 493 | S70: 送金 | T70: ＰＡＮＧＩＬＩＮ | U70: 574.011
A71: ĐLý Việt | B71: 46240 | C71: KH03463 | D71: Maqshood Ali | F71: Cố định | G71: 3292 | H71: 3000 | I71: 292 | J71: 0 | M71: Đơn mới | N71: U00003130106 | O71: 20260806 | P71: 202608060000004 | Q71: 3292 | S71: 送金 | T71: 81961910564ﾆﾂ | U71: 577.303
A72: ĐLý Hoàng | B72: 46240 | C72: KH03517 | D72: Takahashi Maricel Hallig | F72: Cố định | G72: 3797 | H72: 3797 | I72: 0 | J72: 0 | M72: Đơn mới | N72: U00003130103 | O72: 20260806 | P72: 202608060000005 | Q72: 3797 | S72: 送金 | T72: 81961912244ﾆﾂ | U72: 581.1
A73: ĐLý Hoàng | B73: 46240 | C73: KH03530 | D73: Magar Durga Bahadur | F73: Cầm tay | G73: 5252 | H73: 3000 | I73: 2252 | J73: 0 | M73: Đơn mới | O73: 20260806 | P73: 202608060000006 | Q73: 5252 | S73: 送金 | T73: 81961910542ﾆﾂ | U73: 586.352
A74: ĐLý Hoàng | B74: 46240 | C74: KH03539 | D74: Joseph Castro | F74: Cầm tay | G74: 5985 | H74: 3000 | I74: 2985 | J74: 0 | M74: Đơn mới | O74: 20260806 | P74: 202608060000007 | Q74: 5985 | S74: 送金 | T74: 81961910575ﾆﾂ | U74: 592.337
A75: ĐLý Việt | B75: 46240 | C75: KH03516 | D75: SaGar MahaTra ChheTri | F75: Cố định | G75: 3292 | H75: 3000 | I75: 292 | J75: 0 | M75: Đơn mới | N75: U00007885562 | O75: 20260806 | P75: 202608060000008 | Q75: 3292 | S75: 送金 | T75: 81961913084ﾆﾂ | U75: 595.629
A76: ĐLý Hoàng | B76: 46240 | C76: KH03509 | D76: エリカ マリー マイカ | F76: Cầm tay | G76: 6597 | H76: 4000 | I76: 2597 | J76: 0 | M76: Đơn mới | O76: 20260806 | P76: 202608060000009 | Q76: 6597 | S76: 送金 | T76: 81961912266ﾆﾂ | U76: 602.226
A77: ĐLý Việt | B77: 46240 | C77: KH03484 | D77: Qazi Noor Muhammad | F77: Cố định | G77: 3297 | H77: 3297 | I77: 0 | J77: 0 | M77: Đơn mới | N77: U00007895256 | O77: 20260806 | P77: 202608060000010 | Q77: 3297 | S77: 送金 | T77: 81961912325ﾆﾂ | U77: 605.523
A78: ĐLý Hoàng | B78: 46240 | C78: KH03502 | D78: Dilan Dahanayake | F78: Cầm tay | G78: 7092 | H78: 4000 | I78: 3092 | J78: 0 | M78: Đơn mới | O78: 20260806 | P78: 202608060000011 | Q78: 7092 | S78: 送金 | T78: 81961913176ﾆﾂ | U78: 612.615
A79: ĐLý Việt | B79: 46240 | C79: KH03511 | D79: Osep Rosete | F79: Cố định | G79: 3297 | H79: 3297 | I79: 0 | J79: 0 | M79: Đơn mới | N79: U00007882257 | O79: 20260806 | P79: 202608060000012 | Q79: 3297 | S79: 送金 | T79: 81961913121ﾆﾂ | U79: 615.912
A80: ĐLý Việt | B80: 46240 | C80: KH03525 | D80: Kaung Myat San | F80: Cầm tay | G80: 6597 | H80: 4000 | I80: 2597 | J80: 0 | M80: Đơn mới | O80: 20260806 | P80: 202608060000013 | Q80: 6597 | S80: 送金 | T80: 81961912303ﾆﾂ | U80: 622.509
A81: ĐLý Việt | B81: 46240 | C81: KH03448 | D81: 田中 じゃいめ | F81: Cầm tay | G81: 7797 | H81: 4000 | I81: 3797 | J81: 0 | M81: Đơn mới | O81: 20260806 | P81: 202608060000014 | Q81: 7797 | S81: 送金 | T81: 81961913165ﾆﾂ | U81: 630.306
A82: ĐLý Hoàng | B82: 46240 | C82: KH03570 | D82: Võ Minh Khánh | F82: Cố định | G82: 4000 | H82: 4000 | I82: 0 | J82: 0 | M82: Đơn mới | N82: U00007884049 | O82: 20260806 | P82: 202608060000015 | Q82: 4000 | S82: 送金 | T82: ＶＯ ＭＩＮＨ | U82: 634.306
A83: ĐLý Hoàng | B83: 46240 | C83: KH00736 | D83: Dũng Xuân Đinh | F83: Cầm tay | G83: 5695 | H83: 3000 | I83: 2695 | J83: 0 | M83: Đơn mới | O83: 20260806 | P83: 202608060000016 | Q83: 5695 | S83: 送金 | T83: ＬＥ ＶＡＮ Ｌ | U83: 640.001
A84: Công ty | B84: 46240 | C84: KH00538 | D84: Củ Cải | F84: Cầm tay | G84: 2475 | I84: 2475 | J84: 0 | M84: Khách cũ | O84: 20260806 | P84: 202608060000017 | Q84: 2475 | S84: 送金 | T84: ＬＵＵ ＤＩＮＨ | U84: 642.476
A85: Công ty | B85: 46240 | C85: KH01031 | D85: Long Nguyễn | F85: Cầm tay | G85: 2915 | I85: 2915 | J85: 0 | M85: Khách cũ | O85: 20260806 | P85: 202608060000018 | Q85: 2915 | S85: 送金 | T85: ＮＧＵＹＥＮ Ｔ | U85: 645.391
A86: Công ty | B86: 46240 | C86: KH00485 | D86: Nguyễn Thị Thùy Dung | F86: Cầm tay | G86: 2915 | I86: 2915 | J86: 0 | M86: Khách cũ | O86: 20260806 | P86: 202608060000019 | Q86: 2915 | S86: 送金 | T86: ＮＧＵＹＥＮ Ｔ | U86: 648.306
A87: ĐLý Hoàng | B87: 46241 | C87: KH03531 | D87: Benito Étoile Brillant | F87: Cầm tay | G87: 5250 | H87: 3000 | I87: 2250 | J87: 0 | M87: Đơn mới | O87: 20260807 | P87: 202608070000001 | Q87: 5250 | S87: 送金 | T87: 81961910516ﾆﾂ | U87: 653.556
A88: ĐLý tecno | B88: 46241 | C88: KH03542 | D88: Charity Onyebuchi | F88: Cầm tay | G88: 7090 | H88: 4000 | I88: 3090 | J88: 0 | M88: Đơn mới | O88: 20260807 | P88: 202608070000002 | Q88: 7090 | S88: 送金 | T88: 81961910601ﾆﾂ | U88: 660.646
A89: ĐLý Hoàng | B89: 46241 | C89: KH00498 | D89: Nguyễn Vũ | F89: Cầm tay | G89: 6597 | H89: 4000 | I89: 2597 | J89: 0 | M89: Đơn mới | O89: 20260807 | P89: 202608070000003 | Q89: 6597 | S89: 送金 | T89: 81961912270ﾆﾂ | U89: 667.243
A90: ĐLý Việt | B90: 46241 | C90: KH03491 | D90: Arisa Sasaki | F90: Cố định | G90: 3297 | H90: 3297 | I90: 0 | J90: 0 | M90: Đơn mới | N90: U00003130087 | O90: 20260807 | P90: 202608070000004 | Q90: 3297 | S90: 送金 | T90: 81961912314ﾆﾂ | U90: 670.54
A91: ĐLý tecno | B91: 46241 | C91: KH03523 | D91: Sabina Rai | F91: Cầm tay | G91: 5250 | H91: 3000 | I91: 2250 | J91: 0 | M91: Đơn mới | O91: 20260807 | P91: 202608070000005 | Q91: 5250 | S91: 送金 | T91: 81961912281ﾆﾂ | U91: 675.79
A92: Công ty | B92: 46241 | C92: KH00584 | D92: Nguyễn Thị Trang | F92: Cầm tay | G92: 2915 | I92: 2915 | J92: 0 | M92: Khách cũ | O92: 20260807 | P92: 202608070000006 | Q92: 2915 | S92: 送金 | T92: TB01219 | U92: 678.705
A93: Công ty | B93: 46241 | C93: KH00462 | D93: Hoàng Huy | F93: Cầm tay | G93: 2475 | I93: 2475 | J93: 0 | M93: Khách cũ | O93: 20260807 | P93: 202608070000007 | Q93: 2475 | S93: 送金 | T93: ＰＨＡＭ ＶＡＮ | U93: 681.18
A94: ĐLý Việt | B94: 46241 | C94: KH03495 | D94: Nga Moe | F94: Cố định | G94: 500 | H94: 500 | I94: 0 | J94: 0 | M94: Đơn mới | N94: U00007888527 | O94: 20260807 | P94: 202608070000008 | Q94: 500 | S94: 送金 | T94: ＡＵＮＧ ＴＨＥ | U94: 681.68
A95: Công ty | B95: 46241 | C95: KH00990 | D95: Dương Vương Linh | F95: Cầm tay | G95: 2915 | I95: 2915 | J95: 0 | M95: Khách cũ | O95: 20260807 | P95: 202608070000009 | Q95: 2915 | S95: 送金 | T95: ＤＵＯＮＧ ＶＵ | U95: 684.595
A96: Công ty | B96: 46241 | C96: KH00984 | D96: Diệu Linh 2 | F96: Cầm tay | G96: 2475 | I96: 2475 | J96: 0 | M96: Khách cũ | O96: 20260807 | P96: 202608070000010 | Q96: 2475 | S96: 送金 | T96: ＮＧＵＹＥＮ Ｔ | U96: 687.07
A97: Công ty | B97: 46241 | C97: KH00176 | D97: Tâm Antôn | F97: Cầm tay | G97: 2915 | I97: 2915 | J97: 0 | M97: Khách cũ | O97: 20260807 | P97: 202608070000011 | Q97: 2915 | S97: 送金 | T97: ＴＡ ＶＡＮ Ｔ | U97: 689.985
A98: Công ty | B98: 46241 | C98: KH00291 | D98: Trọng Nguyễn | F98: Cầm tay | G98: 2915 | I98: 2915 | J98: 0 | M98: Khách cũ | O98: 20260807 | P98: 202608070000012 | Q98: 2915 | S98: 送金 | T98: ＮＧＵＹＥＮ Ｔ | U98: 692.9
A99: Công ty | B99: 46241 | C99: KH00560 | D99: Phan Thinh | F99: Cầm tay | G99: 2915 | I99: 2915 | J99: 0 | M99: Khách cũ | O99: 20260807 | P99: 202608070000013 | Q99: 2915 | S99: 送金 | T99: ＶＵ ＶＩＥＴ | U99: 695.815
A100: Công ty | B100: 46241 | C100: KH00595 | D100: Vũ Việt Cường | F100: Cầm tay | G100: 2915 | I100: 2915 | J100: 0 | M100: Khách cũ | O100: 20260807 | P100: 202608070000014 | Q100: 2915 | S100: 送金 | T100: ＬＥ ＶＡＮ Ｈ | U100: 698.73
...

Sheet GMO
A1: ĐƠN VỊ | B1: DATE | C1: MÃ KHÁCH HÀNG | D1: TÊN KHÁCH HÀNG | E1: LOẠI DỊCH VỤ | F1: THU | G1: CỌC | H1: CƯỚC | I1: Mã U (NTT) | J1: MÃ GIAO DỊCH
F2: =SUBTOTAL(9,F3:F10000) -> 588803 | G2: =SUBTOTAL(9,G3:G10000) -> 48451 | H2: =SUBTOTAL(9,H3:H10000) -> 540352
A3: Công ty | B3: 46235 | C3: KH02569 | D3: Arshad Mehmood Bhatti | E3: Wifi cố định | F3: 2000 | H3: 2000 | I3: U00007855001 | J3: 1785115561423
A4: ĐLý Hoàng | B4: 46235 | C4: KH03369 | D4: Shabba Meek | E4: Wifi cố định | F4: 2000 | H4: 2000 | I4: U00007843013 | J4: 1785396146511
A5: Công ty | B5: 46235 | C5: KH00349 | D5: Nguyễn Văn Sang | E5: Wifi cố định | F5: 2000 | H5: 2000 | I5: U00007817327 | J5: 1785392650438
A6: Công ty | B6: 46235 | C6: KH01672 | D6: Siyaan Jubiyana | E6: Wifi cầm tay | F6: 3850 | H6: 3850 | J6: 1785546677369
A7: Công ty | B7: 46235 | C7: KH02669 | D7: Na Na | E7: Wifi cố định | F7: 3000 | H7: 3000 | I7: U00007850869 | J7: 1785373882254
A8: ĐLý Hoàng | B8: 46235 | C8: KH03481 | D8: Joebert bringas Imperial | E8: Wifi cầm tay | F8: 8000 | G8: 4000 | H8: 4000 | J8: 1785460890609
A9: Công ty | B9: 46235 | C9: KH03083 | D9: Sally Myat | E9: Wifi cố định | F9: 2000 | H9: 2000 | I9: U00007850382 | J9: 1785512384054
A10: ĐLý Hoàng | B10: 46235 | C10: KH03380 | D10: モット モット | E10: Wifi cầm tay | F10: 5695 | G10: 3000 | H10: 2695 | J10: 1785495792228
A11: ĐLý Việt | B11: 46235 | C11: KH01841 | D11: Jahidul Islam | E11: Wifi cầm tay | F11: 7616 | H11: 7616 | J11: 1785554189437
A12: ĐLý Việt | B12: 46235 | C12: KH03504 | D12: Sandra Liliana Hernández | E12: Wifi cố định | F12: 500 | G12: 500 | I12: U00007892393 | J12: 1785559423378
A13: Công ty | B13: 46235 | C13: KH02469 | D13: Sandesh Rai | E13: Wifi cố định | F13: 2000 | H13: 2000 | I13: U00007835165 | J13: 1785304592709
A14: Công ty | B14: 46235 | C14: KH02966 | D14: Rosalie kato | E14: Wifi cố định | F14: 2000 | H14: 2000 | I14: U00007803797 | J14: 1784958614699
A15: Công ty | B15: 46235 | C15: KH01908 | D15: Cornelius Z. Yoko II | E15: Wifi cố định | F15: 2000 | H15: 2000 | I15: U00007855255 | J15: 1784859962080
A16: Công ty | B16: 46235 | C16: KH02543 | D16: Asam Ahamed | E16: Wifi cố định | F16: 2000 | H16: 2000 | I16: U00007803481 | J16: 1785063481184
A17: ĐLý Việt | B17: 46235 | C17: KH03491 | D17: Arisa Sasaki | E17: Wifi cố định | F17: 500 | G17: 500 | I17: U00007892396 | J17: 1785479596947
A18: ĐLý Hoàng | B18: 46235 | C18: KH03509 | D18: エリカ マリー マイカ | E18: Wifi cầm tay | F18: 493 | H18: 493 | J18: 1785579762217
A19: Công ty | B19: 46235 | C19: KH02441 | D19: Mohamed Anas | E19: Wifi cố định | F19: 2000 | H19: 2000 | I19: U00007871416 | J19: 1785121344444
A20: Công ty | B20: 46235 | C20: KH01880 | D20: Md Shahadat Hossain | E20: Wifi cầm tay | F20: 3850 | H20: 3850 | J20: 1785505762025
A21: ĐLý Hoàng | B21: 46235 | C21: KH03475 | D21: Enriquez Ynnej | E21: Wifi cố định | F21: 2000 | H21: 2000 | I21: U00007804022 | J21: 1785581747932
A22: Công ty | B22: 46235 | C22: KH02237 | D22: Rey Villaver | E22: Wifi cầm tay | F22: 3850 | H22: 3850 | J22: 1785555041516
A23: Công ty | B23: 46235 | C23: KH02134 | D23: Petit Willy | E23: Wifi cố định | F23: 2000 | H23: 2000 | I23: U00007811162 | J23: 1784905956032
A24: Công ty | B24: 46236 | C24: KH02542 | D24: Yumi V. Ogue | E24: Wifi cố định | F24: 2000 | H24: 2000 | I24: U00007819758 | J24: 1784883948457
A25: Công ty | B25: 46236 | C25: KH02205 | D25: Lablab Alexandra | E25: Wifi cố định | F25: 2000 | H25: 2000 | I25: U00007857297 | J25: 1785119355590
A26: Công ty | B26: 46236 | C26: KH02125 | D26: 斎斎 | E26: Wifi cố định | F26: 2000 | H26: 2000 | I26: U00007847235 | J26: 1784983146902
A27: Công ty | B27: 46236 | C27: KH02520 | D27: Bebelyn Okazaki | E27: Wifi cố định | F27: 2000 | H27: 2000 | I27: U00007802607 | J27: 1785550913498
A28: ĐLý Hoàng | B28: 46236 | C28: KH03422 | D28: An Is | E28: Wifi cố định | F28: 2000 | H28: 2000 | I28: U00007794721 | J28: 1785380301800
A29: Công ty | B29: 46236 | C29: KH01964 | D29: Ilham Taka | E29: Wifi cầm tay | F29: 4200 | H29: 4200 | J29: 1785637917320
A30: ĐLý Hoàng | B30: 46236 | C30: KH03130 | D30: Vianca Vernice | E30: Wifi cầm tay | F30: 3850 | H30: 3850 | J30: 1785656644300
A31: Công ty | B31: 46236 | C31: KH01225 | D31: Đức Nguyễn Hữu | E31: Wifi cầm tay | F31: 3850 | H31: 3850 | J31: 1785118537589
A32: Công ty | B32: 46236 | C32: KH02493 | D32: Aboubacar Niakate | E32: Wifi cố định | F32: 2000 | H32: 2000 | I32: U00007811810 | J32: 1784860226637
A33: ĐLý Hoàng | B33: 46237 | C33: KH03213 | D33: imamura adora | E33: Wifi cầm tay | F33: 2800 | H33: 2800 | J33: 1785648913957
A34: Công ty | B34: 46237 | C34: KH02783 | D34: Roselyn Roque Navarro | E34: Wifi cầm tay | F34: 3850 | H34: 3850 | J34: 1785724690239
A35: ĐLý Việt | B35: 46237 | C35: KH03503 | D35: Taritz Matsuzaki | E35: Wifi cố định | F35: 500 | G35: 500 | I35: U00007892203 | J35: 1785559246581
A36: Công ty | B36: 46237 | C36: KH02612 | D36: エシオ チェリ | E36: Wifi cầm tay | F36: 2800 | H36: 2800 | J36: 1785658741422
A37: Công ty | B37: 46237 | C37: KH02883 | D37: Tadz Sndn | E37: Wifi cố định | F37: 2000 | H37: 2000 | I37: U00007819949 | J37: 1785207838734
A38: Công ty | B38: 46237 | C38: KH00794 | D38: Nguyễn Cường | E38: Wifi cầm tay | F38: 2800 | H38: 2800 | J38: 1785723345086
A39: Công ty | B39: 46237 | C39: KH00794 | D39: Nguyễn Cường | E39: Wifi cầm tay | F39: 1077 | H39: 1077 | J39: 1785723345086
A40: Công ty | B40: 46237 | C40: KH00794 | D40: Nguyễn Cường | E40: Wifi cầm tay | F40: 653 | H40: 653 | J40: 1785723345086
A41: Công ty | B41: 46237 | C41: KH02369 | D41: Aki Yamamoto | E41: Wifi cố định | F41: 2000 | H41: 2000 | I41: U00007818869 | J41: 1785746398474
A42: ĐLý Hoàng | B42: 46238 | C42: KH03496 | D42: Muhammad Tarek Abdullah Sakib | E42: Wifi cố định | F42: 2000 | H42: 2000 | I42: U00007871862 | J42: 1785776160693
A43: ĐLý Việt | B43: 46238 | C43: KH03518 | D43: ガマヨ ココロ | E43: Wifi cố định | F43: 500 | G43: 500 | I43: U00007892220 | J43: 1785720771044
A44: Công ty | B44: 46238 | C44: KH02974 | D44: Ranzit Gurung | E44: Wifi cố định | F44: 2000 | H44: 2000 | I44: U00007790110 | J44: 1785135753025
A45: ĐLý Hoàng | B45: 46238 | C45: KH03349 | D45: Flordeliza Lorica | E45: Wifi cố định | F45: 2000 | H45: 2000 | I45: U00007867132 | J45: 1785047180576
A46: Công ty | B46: 46238 | C46: KH02664 | D46: Mc DO | E46: Wifi cố định | F46: 3000 | H46: 3000 | I46: U00007839551 | J46: 1785733508728
A47: ĐLý Việt | B47: 46238 | C47: KH02955 | D47: Kitty Ho | E47: Wifi cầm tay | F47: 3850 | H47: 3850 | J47: 1785743249776
A48: Công ty | B48: 46238 | C48: KH02179 | D48: Wiwut Ruangpakdee | E48: Wifi cố định | F48: 2000 | H48: 2000 | I48: U00007815988 | J48: 1784954418365
A49: ĐLý Việt | B49: 46238 | C49: KH03459 | D49: Aditia Ramasaputra | E49: Wifi cố định | F49: 2000 | H49: 2000 | I49: U00007858437 | J49: 1785512625186
A50: Công ty | B50: 46238 | C50: KH02461 | D50: Deepak Ramtel | E50: Wifi cố định | F50: 2000 | H50: 2000 | I50: U00007812090 | J50: 1785121437750
A51: Công ty | B51: 46238 | C51: KH02037 | D51: 鈴木 ビビ | E51: Wifi cố định | F51: 2000 | H51: 2000 | I51: U00007813154 | J51: 1784855607959
A52: ĐLý Việt | B52: 46238 | C52: KH03547 | D52: Purushotam Chaudhary | E52: Wifi cố định | F52: 2000 | H52: 2000 | I52: U00007797907 | J52: 1785807289965
A53: Công ty | B53: 46238 | C53: KH02871 | D53: Aj Avila | E53: Wifi cầm tay | F53: 3850 | H53: 3850 | J53: 1785394701752
A54: Công ty | B54: 46238 | C54: KH02871 | D54: Aj Avila | E54: Wifi cố định | F54: 4000 | H54: 4000 | I54: U00007857706 | J54: 1785394701752
A55: Công ty | B55: 46238 | C55: KH02137 | D55: Habib Ullah | E55: Wifi cố định | F55: 2000 | H55: 2000 | I55: U00007818265 | J55: 1785316270497
A56: Công ty | B56: 46238 | C56: KH03003 | D56: Shahid Islam | E56: Wifi cố định | F56: 2000 | H56: 2000 | I56: U00007841237 | J56: 1784884946919
A57: ĐLý Việt | B57: 46238 | C57: KH03526 | D57: Jenny Flores | E57: Wifi cố định | F57: 3000 | G57: 3000 | I57: U00007892177 | J57: 1785823675100
A58: ĐLý Việt | B58: 46238 | C58: KH03534 | D58: Clint Philip Guba Ladera | E58: Wifi cố định | F58: 2000 | H58: 2000 | I58: U00007861234 | J58: 1784977135578
A59: ĐLý Hoàng | B59: 46238 | C59: KH03418 | D59: Manuel Iwanaga | E59: Wifi cố định | F59: 2000 | H59: 2000 | I59: U00007858258 | J59: 1785853445097
A60: Công ty | B60: 46239 | C60: KH03076 | D60: Sultan Mizuno | E60: Wifi cố định | F60: 2000 | H60: 2000 | I60: U00007858661 | J60: 1784885964662
A61: Công ty | B61: 46239 | C61: KH02359 | D61: Vanchan Dayo | E61: Wifi cố định | F61: 2000 | H61: 2000 | I61: U00007815988 | J61: 1785218581445
A62: ĐLý Hoàng | B62: 46239 | C62: KH03410 | D62: Mohamed Nazim モハメド・ニヤス | E62: Wifi cố định | F62: 3000 | H62: 3000 | I62: U00007855400 | J62: 1784983488361
A63: ĐLý Việt | B63: 46239 | C63: KH02646 | D63: ユアせ マリア | E63: Wifi cố định | F63: 3000 | H63: 3000 | I63: U00007848376 | J63: 1785852169238
A64: Công ty | B64: 46239 | C64: KH02209 | D64: Nayomi Rajapaksha | E64: Wifi cố định | F64: 2000 | H64: 2000 | I64: U00007825013 | J64: 1785826116266
A65: Công ty | B65: 46239 | C65: KH02258 | D65: Levis Ramirez Montalvan | E65: Wifi cầm tay | F65: 3850 | H65: 3850 | J65: 1785913123837
A66: ĐLý Việt | B66: 46239 | C66: KH03550 | D66: Richard Danao | E66: Wifi cố định | F66: 4000 | G66: 4000 | I66: U00007892181 | J66: 1785901652460
A67: Công ty | B67: 46239 | C67: KH00781 | D67: Đào Tuấn Giottinhxanh | E67: Wifi cầm tay | F67: 2915 | H67: 2915 | J67: 1785901747111
A68: ĐLý Việt | B68: 46239 | C68: KH03522 | D68: Iris Airi Garcia | E68: Wifi cố định | F68: 500 | G68: 500 | I68: U00007892169 | J68: 1785723755058
A69: Công ty | B69: 46239 | C69: KH00928 | D69: Nguyenquang Hanh | E69: Wifi cầm tay | F69: 5830 | H69: 5830 | J69: 1785902145923
A70: ĐLý Hoàng | B70: 46239 | C70: KH03545 | D70: Khalid Hawlader | E70: Wifi cố định | F70: 500 | G70: 500 | I70: U00007892135 | J70: 1785918707093
A71: Công ty | B71: 46239 | C71: KH01722 | D71: Hoàn Xuân Nguyễn | E71: Wifi cầm tay | F71: 2475 | H71: 2475 | J71: 1785828313490
A72: ĐLý Việt | B72: 46239 | C72: KH01764 | D72: Migara Bandar | E72: Wifi cố định | F72: 500 | G72: 500 | I72: U00007891952 | J72: 1785920793232
A73: Công ty | B73: 46239 | C73: KH02313 | D73: Arthuro Yamaguchi | E73: Wifi cố định | F73: 2000 | H73: 2000 | I73: U00007854206 | J73: 1785378997190
A74: Công ty | B74: 46239 | C74: KH02299 | D74: Enmir Castro | E74: Wifi cố định | F74: 2000 | H74: 2000 | I74: U00007802832 | J74: 1785563698244
A75: ĐLý Việt | B75: 46239 | C75: KH03554 | D75: Chhetri Rajiv | E75: Wifi cố định | F75: 4000 | G75: 4000 | I75: U00007891911 | J75: 1785814756078
A76: Công ty | B76: 46239 | C76: KH01973 | D76: TasFiqul Ahmed | E76: Wifi cố định | F76: 2000 | H76: 2000 | I76: U00007820381 | J76: 1785467242848
A77: Công ty | B77: 46239 | C77: KH03273 | D77: ジュリ 江川 | E77: Wifi cố định | F77: 3000 | H77: 3000 | I77: U00007857194 | J77: 1785132594945
A78: Công ty | B78: 46239 | C78: KH00781 | D78: Đào Tuấn Giottinhxanh | E78: Wifi cầm tay | F78: 5830 | H78: 5830 | J78: 1785828321776
A79: Công ty | B79: 46239 | C79: KH02729 | D79: Isuru Hiran Ranasinghe | E79: Wifi cố định | F79: 2000 | H79: 2000 | I79: U00007830494 | J79: 1784976656318
A80: ĐLý Hoàng | B80: 46239 | C80: KH02563 | D80: ธนภรณ์ เจตประพันธ์ | E80: Wifi cầm tay | F80: 4960 | G80: 3000 | H80: 1960 | J80: 1785916251103
A81: ĐLý Việt | B81: 46240 | C81: KH03544 | D81: Gertrude Kyei | E81: Wifi cố định | F81: 2000 | H81: 2000 | I81: U00007802820 | J81: 1785399029520
A82: ĐLý Việt | B82: 46240 | C82: KH03564 | D82: Kristostomus Katuuk | E82: Wifi cầm tay | F82: 493 | G82: 493 | J82: 1785928449369
A83: Công ty | B83: 46240 | C83: KH01996 | D83: Richie Richard | E83: Wifi cố định | F83: 2000 | H83: 2000 | I83: U00007799781 | J83: 1785838033221
A84: ĐLý Hoàng | B84: 46240 | C84: KH03404 | D84: Maria Victoria Giron | E84: Wifi cố định | F84: 6000 | H84: 6000 | I84: U00007855453 | J84: 1785858602012
A85: ĐLý Việt | B85: 46240 | C85: KH03548 | D85: 彭聖凱 | E85: Wifi cố định | F85: 500 | G85: 500 | I85: U00007891904 | J85: 1785893695010
A86: ĐLý Hoàng | B86: 46240 | C86: KH03096 | D86: Mhii Jiin | E86: Wifi cố định | F86: 2000 | H86: 2000 | I86: U00007853337 | J86: 1785892951046
A87: ĐLý Việt | B87: 46240 | C87: KH03538 | D87: Nolando Okamoto Rabonza | E87: Wifi cố định | F87: 2000 | H87: 2000 | I87: U00007813346 | J87: 1785819438267
A88: ĐLý Hoàng | B88: 46240 | C88: KH03251 | D88: Muqtadir Al Mehran Mahee | E88: Wifi cố định | F88: 3000 | H88: 3000 | I88: U00007855173 | J88: 1786004402803
A89: Công ty | B89: 46240 | C89: KH00780 | D89: Nguyễn AhhTuấn | E89: Wifi cầm tay | F89: 2915 | H89: 2915 | J89: 1785828267100
A90: Công ty | B90: 46240 | C90: KH00074 | D90: Phúc Lâm | E90: Wifi cầm tay | F90: 2475 | H90: 2475 | J90: 1785828385508
A91: Công ty | B91: 46240 | C91: KH02260 | D91: Mer Cy | E91: Wifi cố định | F91: 2000 | H91: 2000 | I91: U00007803100 | J91: 1784884090955
A92: ĐLý Hoàng | B92: 46240 | C92: KH03573 | D92: Laurence Brixx de Cats | E92: Wifi cố định | F92: 2000 | H92: 2000 | I92: U00007850487 | J92: 1785992131847
A93: ĐLý tecno | B93: 46240 | C93: KH03560 | D93: Dibyaswar Subedi | E93: Wifi cố định | F93: 2000 | H93: 2000 | I93: U00007854205 | J93: 1785919349196
A94: Công ty | B94: 46240 | C94: KH01609 | D94: Mic Hael | E94: Wifi cầm tay | F94: 3850 | H94: 3850 | J94: 1786008611101
A95: Công ty | B95: 46240 | C95: KH02483 | D95: Ai Rosalina | E95: Wifi cố định | F95: 2000 | H95: 2000 | I95: U00007821818 | J95: 1784863024889
A96: ĐLý Hoàng | B96: 46240 | C96: KH03323 | D96: Jeboy Moreno Chiqo | E96: Wifi cầm tay | F96: 6850 | G96: 3000 | H96: 3850 | J96: 1784709665187
A97: ĐLý Hoàng | B97: 46240 | C97: KH03489 | D97: Narendra Kunwar | E97: Wifi cố định | F97: 2000 | H97: 2000 | I97: U00007857302 | J97: 1785812039192
A98: ĐLý Hoàng | B98: 46240 | C98: KH03536 | D98: Bé Thuỷ | E98: Wifi cố định | F98: 2000 | H98: 2000 | I98: U00007850487 | J98: 1785816264246
A99: Công ty | B99: 46240 | C99: KH02040 | D99: Nguyễn KT | E99: Wifi cố định | F99: 2000 | H99: 2000 | I99: U00007859770 | J99: 1784859174531
A100: Công ty | B100: 46240 | C100: KH02214 | D100: Saman サマン | E100: Wifi cầm tay | F100: 3850 | H100: 3850 | J100: 1785828928559
...

Sheet SBI
A1: ĐƠN VỊ | B1: NGÀY THÁNG | C1: NỘI DUNG | E1: MÃ KH | F1: TÊN KH | G1: LOẠI DỊCH VỤ | H1: THU | I1: CHI | J1: NOTE
H2: =SUBTOTAL(9,H3:H201) -> 6656563 | I2: =SUBTOTAL(9,I3:I201) -> 7228354 | N2: CHI | O2: THU
A3: Công ty | B3: =L3 -> 46237 | C3: =M3 -> 口座振替 シヤープフアイナンス | E3: CTY | F3: 3m intel | G3: Khác | H3: =O3 -> 0 | I3: =N3 -> 10890 | J3: Tiền thuê máy in | L3: 46237 | M3: 口座振替 シヤープフアイナンス | N3: 10890 | P3: 1528658 | Q3: -
A4: Công ty | B4: =L4 -> 46237 | C4: =M4 -> 振込＊チヤン テイ マイ チユオン | E4: CTY | F4: 3m intel | G4: Khác | H4: =O4 -> 0 | I4: =N4 -> 81880 | J4: Chuyển tiền vận chuyển cho kho | L4: 46237 | M4: 振込＊チヤン テイ マイ チユオン | N4: 81880 | P4: 1446778 | Q4: 経費精算
A5: Công ty | B5: =L5 -> 46237 | C5: =M5 -> 振込手数料 | E5: CTY | F5: 3m intel | G5: Khác | H5: =O5 -> 0 | I5: =N5 -> 140 | J5: Phí chuyển tiền | L5: 46237 | M5: 振込手数料 | N5: 140 | P5: 1446638 | Q5: -
A6: Công ty | B6: =L6 -> 46237 | C6: =M6 -> 振込＊クボ シヤロン エスプラゴサ | E6: CTY | F6: 3m intel | G6: Khác | H6: =O6 -> 0 | I6: =N6 -> 3000 | J6: Hoàn cọc | L6: 46237 | M6: 振込＊クボ シヤロン エスプラゴサ | N6: 3000 | P6: 1443638 | Q6: デポジット返金
A7: Công ty | B7: =L7 -> 46237 | C7: =M7 -> 振込手数料 | E7: CTY | F7: 3m intel | G7: Khác | H7: =O7 -> 0 | I7: =N7 -> 140 | J7: Phí chuyển tiền | L7: 46237 | M7: 振込手数料 | N7: 140 | P7: 1443498 | Q7: -
A8: Công ty | B8: =L8 -> 46237 | C8: =M8 -> 振込＊グエン ザー フオン | E8: CTY | F8: 3m intel | G8: Khác | H8: =O8 -> 0 | I8: =N8 -> 4000 | J8: Hoàn cọc | L8: 46237 | M8: 振込＊グエン ザー フオン | N8: 4000 | P8: 1439498 | Q8: デポジット返金
A9: Công ty | B9: =L9 -> 46237 | C9: =M9 -> 振込手数料 | E9: CTY | F9: 3m intel | G9: Khác | H9: =O9 -> 0 | I9: =N9 -> 140 | J9: Phí chuyển tiền | L9: 46237 | M9: 振込手数料 | N9: 140 | P9: 1439358 | Q9: -
A10: Công ty | B10: =L10 -> 46237 | C10: =M10 -> デビット ８３５１６２ | E10: CTY | F10: 3m intel | G10: Khác | H10: =O10 -> 0 | I10: =N10 -> 185 | J10: Cước vận chuyển | L10: 46237 | M10: デビット ８３５１６２ | N10: 185 | P10: 1439173 | Q10: -
A11: Công ty | B11: =L11 -> 46237 | C11: =M11 -> デビット ８３５７９０ | E11: CTY | F11: 3m intel | G11: Khác | H11: =O11 -> 0 | I11: =N11 -> 185 | J11: Cước vận chuyển | L11: 46237 | M11: デビット ８３５７９０ | N11: 185 | P11: 1438988 | Q11: -
A12: Công ty | B12: =L12 -> 46237 | C12: =M12 -> デビット ８４１５９８ | E12: CTY | F12: 3m intel | G12: Khác | H12: =O12 -> 0 | I12: =N12 -> 185 | J12: Cước vận chuyển | L12: 46237 | M12: デビット ８４１５９８ | N12: 185 | P12: 1438803 | Q12: -
A13: Công ty | B13: =L13 -> 46237 | C13: =M13 -> デビット ８４３７９２ | E13: CTY | F13: 3m intel | G13: Khác | H13: =O13 -> 0 | I13: =N13 -> 185 | J13: Cước vận chuyển | L13: 46237 | M13: デビット ８４３７９２ | N13: 185 | P13: 1438618 | Q13: -
A14: Công ty | B14: =L14 -> 46237 | C14: =M14 -> デビット ８４４３３４ | E14: CTY | F14: 3m intel | G14: Khác | H14: =O14 -> 0 | I14: =N14 -> 185 | J14: Cước vận chuyển | L14: 46237 | M14: デビット ８４４３３４ | N14: 185 | P14: 1438433 | Q14: -
... A27: Công ty | B27: =L27 -> 46238 | C27: =M27 -> デビット ０７８５７９ | E27: CTY | F27: 3m intel | G27: Khác | H27: =O27 -> 0 | I27: =N27 -> 185 | J27: Cước vận chuyển | L27: 46238 | M27: デビット ０７８５７９ | N27: 185 | P27: 1436028 | Q27: -
A28: Công ty | B28: =L28 -> 46239 | C28: =M28 -> デビット ３０９９８６ | E28: CTY | F28: 3m intel | G28: Khác | H28: =O28 -> 0 | I28: =N28 -> 185 | J28: Cước vận chuyển | L28: 46239 | M28: デビット ３０９９８６ | N28: 185 | P28: 1435843
A29: Công ty | B29: =L29 -> 46239 | C29: =M29 -> デビット ３３１９０９ | E29: CTY | F29: 3m intel | G29: Khác | H29: =O29 -> 0 | I29: =N29 -> 185 | J29: Cước vận chuyển | L29: 46239 | M29: デビット ３３１９０９ | N29: 185 | P29: 1435658
A30: Công ty | B30: =L30 -> 46239 | C30: =M30 -> デビット ３３２５９４ | E30: CTY | F30: 3m intel | G30: Khác | H30: =O30 -> 0 | I30: =N30 -> 185 | J30: Cước vận chuyển | L30: 46239 | M30: デビット ３３２５９４ | N30: 185 | P30: 1435473
A31: Công ty | B31: =L31 -> 46240 | C31: =M31 -> デビット ５８９４５６ | E31: CTY | F31: 3m intel | G31: Khác | H31: =O31 -> 0 | I31: =N31 -> 185 | J31: Cước vận chuyển | L31: 46240 | M31: デビット ５８９４５６ | N31: 185 | P31: 1435288
A32: Công ty | B32: =L32 -> 46240 | C32: =M32 -> デビット ５９０３５６ | E32: CTY | F32: 3m intel | G32: Khác | H32: =O32 -> 0 | I32: =N32 -> 185 | J32: Cước vận chuyển | L32: 46240 | M32: デビット ５９０３５６ | N32: 185 | P32: 1435103
A33: Công ty | B33: =L33 -> 46240 | C33: =M33 -> デビット ５９１０３３ | E33: CTY | F33: 3m intel | G33: Khác | H33: =O33 -> 0 | I33: =N33 -> 185 | J33: Cước vận chuyển | L33: 46240 | M33: デビット ５９１０３３ | N33: 185 | P33: 1434918
A34: Công ty | B34: =L34 -> 46240 | C34: =M34 -> デビット ６０９３０９ | E34: CTY | F34: 3m intel | G34: Khác | H34: =O34 -> 0 | I34: =N34 -> 185 | J34: Cước vận chuyển | L34: 46240 | M34: デビット ６０９３０９ | N34: 185 | P34: 1434733
A35: Công ty | B35: =L35 -> 46240 | C35: =M35 -> デビット ６２３２５２ | E35: CTY | F35: 3m intel | G35: Khác | H35: =O35 -> 0 | I35: =N35 -> 185 | J35: Cước vận chuyển | L35: 46240 | M35: デビット ６２３２５２ | N35: 185 | P35: 1434548
A36: Công ty | B36: =L36 -> 46240 | C36: =M36 -> デビット ６３２６００ | E36: CTY | F36: 3m intel | G36: Khác | H36: =O36 -> 0 | I36: =N36 -> 185 | J36: Cước vận chuyển | L36: 46240 | M36: デビット ６３２６００ | N36: 185 | P36: 1434363
A37: Công ty | B37: =L37 -> 46240 | C37: =M37 -> デビット ６３４１１１ | E37: CTY | F37: 3m intel | G37: Khác | H37: =O37 -> 0 | I37: =N37 -> 185 | J37: Cước vận chuyển | L37: 46240 | M37: デビット ６３４１１１ | N37: 185 | P37: 1434178
A38: Công ty | B38: =L38 -> 46240 | C38: =M38 -> デビット ６３６７０７ | E38: CTY | F38: 3m intel | G38: Khác | H38: =O38 -> 0 | I38: =N38 -> 185 | J38: Cước vận chuyển | L38: 46240 | M38: デビット ６３６７０７ | N38: 185 | P38: 1433993
A39: Công ty | B39: =L39 -> 46240 | C39: =M39 -> デビット ６３７２６１ | E39: CTY | F39: 3m intel | G39: Khác | H39: =O39 -> 0 | I39: =N39 -> 185 | J39: Cước vận chuyển | L39: 46240 | M39: デビット ６３７２６１ | N39: 185 | P39: 1433808
A40: Công ty | B40: =L40 -> 46240 | C40: =M40 -> 取消＊デビット ８６０９５９ | E40: CTY | F40: 3m intel | G40: Khác | H40: =O40 -> 185 | I40: =N40 -> 0 | J40: Cước vận chuyển | L40: 46240 | M40: 取消＊デビット ８６０９５９ | O40: 185 | P40: 1433993
A41: Công ty | B41: =L41 -> 46240 | C41: =M41 -> 振込＊テキ（カ | E41: TEKI | G41: Cầm tay | H41: =O41 -> 705651 | I41: =N41 -> 0 | J41: Công nợ tháng 7 Teki | L41: 46240 | M41: 振込＊テキ（カ | O41: 705651 | P41: 2139644
A42: Công ty | B42: =L42 -> 46241 | C42: =M42 -> 振込＊チヤン テイ マイ チユオン | E42: CTY | F42: 3m intel | G42: Khác | H42: =O42 -> 0 | I42: =N42 -> 93555 | J42: Chuyển tiền vận chuyển cho kho | L42: 46241 | M42: 振込＊チヤン テイ マイ チユオン | N42: 93555 | P42: 2046089
A43: Công ty | B43: =L43 -> 46241 | C43: =M43 -> 振込手数料 | E43: CTY | F43: 3m intel | G43: Khác | H43: =O43 -> 0 | I43: =N43 -> 140 | J43: Phí chuyển tiền | L43: 46241 | M43: 振込手数料 | N43: 140 | P43: 2045949
A44: Công ty | B44: =L44 -> 46241 | C44: =M44 -> デビット ８９２５６３ | E44: CTY | F44: 3m intel | G44: Khác | H44: =O44 -> 0 | I44: =N44 -> 185 | J44: Cước vận chuyển | L44: 46241 | M44: デビット ８９２５６３ | N44: 185 | P44: 2045764
A45: Công ty | B45: =L45 -> 46241 | C45: =M45 -> デビット ８９９２８３ | E45: CTY | F45: 3m intel | G45: Khác | H45: =O45 -> 0 | I45: =N45 -> 185 | J45: Cước vận chuyển | L45: 46241 | M45: デビット ８９９２８３ | N45: 185 | P45: 2045579
A46: Công ty | B46: =L46 -> 46241 | C46: =M46 -> デビット ９００１１２ | E46: CTY | F46: 3m intel | G46: Khác | H46: =O46 -> 0 | I46: =N46 -> 185 | J46: Cước vận chuyển | L46: 46241 | M46: デビット ９００１１２ | N46: 185 | P46: 2045394
A47: Công ty | B47: =L47 -> 46241 | C47: =M47 -> デビット ９４０２３０ | E47: CTY | F47: 3m intel | G47: Khác | H47: =O47 -> 0 | I47: =N47 -> 185 | J47: Cước vận chuyển | L47: 46241 | M47: デビット ９４０２３０ | N47: 185 | P47: 2045209
A48: Công ty | B48: =L48 -> 46241 | C48: =M48 -> デビット ９４１５３６ | E48: CTY | F48: 3m intel | G48: Khác | H48: =O48 -> 0 | I48: =N48 -> 185 | J48: Cước vận chuyển | L48: 46241 | M48: デビット ９４１５３６ | N48: 185 | P48: 2045024
A49: Công ty | B49: =L49 -> 46241 | C49: =M49 -> デビット ９４３４７３ | E49: CTY | F49: 3m intel | G49: Khác | H49: =O49 -> 0 | I49: =N49 -> 185 | J49: Cước vận chuyển | L49: 46241 | M49: デビット ９４３４７３ | N49: 185 | P49: 2044839
A50: Công ty | B50: =L50 -> 46241 | C50: =M50 -> デビット ９４４７２０ | E50: CTY | F50: 3m intel | G50: Khác | H50: =O50 -> 0 | I50: =N50 -> 185 | J50: Cước vận chuyển | L50: 46241 | M50: デビット ９４４７２０ | N50: 185 | P50: 2044654
A51: Công ty | B51: =L51 -> 46241 | C51: =M51 -> デビット ９４６０３７ | E51: CTY | F51: 3m intel | G51: Khác | H51: =O51 -> 0 | I51: =N51 -> 185 | J51: Cước vận chuyển | L51: 46241 | M51: デビット ９４６０３７ | N51: 185 | P51: 2044469
A52: Công ty | B52: =L52 -> 46241 | C52: =M52 -> デビット ９４７３４７ | E52: CTY | F52: 3m intel | G52: Khác | H52: =O52 -> 0 | I52: =N52 -> 185 | J52: Cước vận chuyển | L52: 46241 | M52: デビット ９４７３４７ | N52: 185 | P52: 2044284
A53: Công ty | B53: =L53 -> 46241 | C53: =M53 -> デビット ９５０３５９ | E53: CTY | F53: 3m intel | G53: Khác | H53: =O53 -> 0 | I53: =N53 -> 185 | J53: Cước vận chuyển | L53: 46241 | M53: デビット ９５０３５９ | N53: 185 | P53: 2044099
A54: Công ty | B54: =L54 -> 46241 | C54: =M54 -> デビット ０４１２３２ | E54: CTY | F54: 3m intel | G54: Khác | H54: =O54 -> 0 | I54: =N54 -> 2424 | J54: Cước vận chuyển | L54: 46241 | M54: デビット ０４１２３２ | N54: 2424 | P54: 2041675
A55: Công ty | B55: =L55 -> 46244 | C55: =M55 -> デビット ８３１１４４ | E55: CTY | F55: 3m intel | G55: Khác | H55: =O55 -> 0 | I55: =N55 -> 185 | J55: Cước vận chuyển | L55: 46244 | M55: デビット ８３１１４４ | N55: 185 | P55: 2139008 | Q55: -
A56: Công ty | B56: =L56 -> 46244 | C56: =M56 -> デビット ８３０５２３ | E56: CTY | F56: 3m intel | G56: Khác | H56: =O56 -> 0 | I56: =N56 -> 185 | J56: Cước vận chuyển | L56: 46244 | M56: デビット ８３０５２３ | N56: 185 | P56: 2139193 | Q56: -
A57: Công ty | B57: =L57 -> 46244 | C57: =M57 -> デビット ８２９９２６ | E57: CTY | F57: 3m intel | G57: Khác | H57: =O57 -> 0 | I57: =N57 -> 185 | J57: Cước vận chuyển | L57: 46244 | M57: デビット ８２９９２６ | N57: 185 | P57: 2139378 | Q57: -
A58: Công ty | B58: =L58 -> 46244 | C58: =M58 -> デビット ８２９３６０ | E58: CTY | F58: 3m intel | G58: Khác | H58: =O58 -> 0 | I58: =N58 -> 185 | J58: Cước vận chuyển | L58: 46244 | M58: デビット ８２９３６０ | N58: 185 | P58: 2139563 | Q58: -
A59: Công ty | B59: =L59 -> 46244 | C59: =M59 -> デビット ８２８７４２ | E59: CTY | F59: 3m intel | G59: Khác | H59: =O59 -> 0 | I59: =N59 -> 185 | J59: Cước vận chuyển | L59: 46244 | M59: デビット ８２８７４２ | N59: 185 | P59: 2139748 | Q59: -
A60: Công ty | B60: =L60 -> 46244 | C60: =M60 -> 振込＊エヌテイキユーエツクス（ド | E60: Đại lý Trưởng | G60: Cầm tay | H60: =O60 -> 98258 | I60: =N60 -> 0 | J60: Công nợ tháng 7 Trưởng | L60: 46244 | M60: 振込＊エヌテイキユーエツクス（ド | O60: 98258 | P60: 2139933 | Q60: -
A61: Công ty | B61: =L61 -> 46245 | C61: =M61 -> デビット １３４９４５ | E61: CTY | F61: 3m intel | G61: Khác | H61: =O61 -> 0 | I61: =N61 -> 185 | J61: Cước vận chuyển | L61: 46245 | M61: デビット １３４９４５ | N61: 185 | P61: 2138268 | Q61: -
A62: Công ty | B62: =L62 -> 46245 | C62: =M62 -> デビット ０８７４２５ | E62: CTY | F62: 3m intel | G62: Khác | H62: =O62 -> 0 | I62: =N62 -> 185 | J62: Cước vận chuyển | L62: 46245 | M62: デビット ０８７４２５ | N62: 185 | P62: 2138453 | Q62: -
A63: Công ty | B63: =L63 -> 46245 | C63: =M63 -> デビット ０８６９４６ | E63: CTY | F63: 3m intel | G63: Khác | H63: =O63 -> 0 | I63: =N63 -> 185 | J63: Cước vận chuyển | L63: 46245 | M63: デビット ０８６９４６ | N63: 185 | P63: 2138638 | Q63: -
A64: Công ty | B64: =L64 -> 46245 | C64: =M64 -> デビット ０８４５１２ | E64: CTY | F64: 3m intel | G64: Khác | H64: =O64 -> 0 | I64: =N64 -> 185 | J64: Cước vận chuyển | L64: 46245 | M64: デビット ０８４５１２ | N64: 185 | P64: 2138823 | Q64: -
A65: Công ty | B65: =L65 -> 46246 | C65: =M65 -> 取消＊デビット ７３７４３４ | E65: CTY | F65: 3m intel | G65: Khác | H65: =O65 -> 185 | I65: =N65 -> 0 | J65: Cước vận chuyển | L65: 46246 | M65: 取消＊デビット ７３７４３４ | O65: 185 | P65: 2137158 | Q65: -
A66: Công ty | B66: =L66 -> 46246 | C66: =M66 -> デビット ４１３０８１ | E66: CTY | F66: 3m intel | G66: Khác | H66: =O66 -> 0 | I66: =N66 -> 185 | J66: Cước vận chuyển | L66: 46246 | M66: デビット ４１３０８１ | N66: 185 | P66: 2136973 | Q66: -
A67: Công ty | B67: =L67 -> 46246 | C67: =M67 -> デビット ４１２５８９ | E67: CTY | F67: 3m intel | G67: Khác | H67: =O67 -> 0 | I67: =N67 -> 185 | J67: Cước vận chuyển | L67: 46246 | M67: デビット ４１２５８９ | N67: 185 | P67: 2137158 | Q67: -
A68: Công ty | B68: =L68 -> 46246 | C68: =M68 -> デビット ３９６６５２ | E68: CTY | F68: 3m intel | G68: Khác | H68: =O68 -> 0 | I68: =N68 -> 185 | J68: Cước vận chuyển | L68: 46246 | M68: デビット ３９６６５２ | N68: 185 | P68: 2137343 | Q68: -
A69: Công ty | B69: =L69 -> 46246 | C69: =M69 -> デビット ３８２５５９ | E69: CTY | F69: 3m intel | G69: Khác | H69: =O69 -> 0 | I69: =N69 -> 185 | J69: Cước vận chuyển | L69: 46246 | M69: デビット ３８２５５９ | N69: 185 | P69: 2137528 | Q69: -
A70: Công ty | B70: =L70 -> 46246 | C70: =M70 -> デビット ３６１９５５ | E70: CTY | F70: 3m intel | G70: Khác | H70: =O70 -> 0 | I70: =N70 -> 185 | J70: Cước vận chuyển | L70: 46246 | M70: デビット ３６１９５５ | N70: 185 | P70: 2137713 | Q70: -
A71: Công ty | B71: =L71 -> 46246 | C71: =M71 -> デビット ３５９９１４ | E71: CTY | F71: 3m intel | G71: Khác | H71: =O71 -> 0 | I71: =N71 -> 185 | J71: Cước vận chuyển | L71: 46246 | M71: デビット ３５９９１４ | N71: 185 | P71: 2137898 | Q71: -
A72: Công ty | B72: =L72 -> 46246 | C72: =M72 -> デビット ３５４４２９ | E72: CTY | F72: 3m intel | G72: Khác | H72: =O72 -> 0 | I72: =N72 -> 185 | J72: Cước vận chuyển | L72: 46246 | M72: デビット ３５４４２９ | N72: 185 | P72: 2138083 | Q72: -
A73: Công ty | B73: =L73 -> 46247 | C73: =M73 -> デビット ６６６５３６ | E73: CTY | F73: 3m intel | G73: Khác | H73: =O73 -> 0 | I73: =N73 -> 185 | J73: Cước vận chuyển | L73: 46247 | M73: デビット ６６６５３６ | N73: 185 | P73: 2136233 | Q73: -
A74: Công ty | B74: =L74 -> 46247 | C74: =M74 -> デビット ６６５８６９ | E74: CTY | F74: 3m intel | G74: Khác | H74: =O74 -> 0 | I74: =N74 -> 185 | J74: Cước vận chuyển | L74: 46247 | M74: デビット ６６５８６９ | N74: 185 | P74: 2136418 | Q74: -
A75: Công ty | B75: =L75 -> 46247 | C75: =M75 -> デビット ６５５３３７ | E75: CTY | F75: 3m intel | G75: Khác | H75: =O75 -> 0 | I75: =N75 -> 185 | J75: Cước vận chuyển | L75: 46247 | M75: デビット ６５５３３７ | N75: 185 | P75: 2136603 | Q75: -
A76: Công ty | B76: =L76 -> 46247 | C76: =M76 -> デビット ６４８８８２ | E76: CTY | F76: 3m intel | G76: Khác | H76: =O76 -> 0 | I76: =N76 -> 185 | J76: Cước vận chuyển | L76: 46247 | M76: デビット ６４８８８２ | N76: 185 | P76: 2136788 | Q76: -
A77: Công ty | B77: =L77 -> 46247 | C77: =M77 -> デビット ６４８１８９ | E77: CTY | F77: 3m intel | G77: Khác | H77: =O77 -> 0 | I77: =N77 -> 185 | J77: Cước vận chuyển | L77: 46247 | M77: デビット ６４８１８９ | N77: 185 | P77: 2136973 | Q77: -
... A83: Công ty | B83: =L83 -> 46250 | C83: =M83 -> 国税 | E83: CTY | F83: 3m intel | G83: Khác | H83: =O83 -> 0 | I83: =N83 -> 107 | J83: Phí ngân hàng | L83: 46250 | M83: 国税 | N83: 107 | P83: 2135901 | Q83: -
A84: Công ty | B84: =L84 -> 46250 | C84: =M84 -> 利息 | E84: KH01005 | F84: Huy Đỗ | G84: Cầm tay | H84: =O84 -> 700 | I84: =N84 -> 0 | J84: Thu cước | L84: 46250 | M84: 利息 | O84: 700 | P84: 2136008 | Q84: -
A85: Công ty | B85: =L85 -> 46251 | C85: =M85 -> 取消＊デビット １２３３８６ | E85: CTY | F85: 3m intel | G85: Khác | H85: =O85 -> 185 | I85: =N85 -> 0 | J85: Cước vận chuyển | L85: 46251 | M85: 取消＊デビット １２３３８６ | O85: 185 | P85: 4286643 | Q85: -
A86: Công ty | B86: =L86 -> 46251 | C86: =M86 -> デビット ８１２０８０ | E86: CTY | F86: 3m intel | G86: Khác | H86: =O86 -> 0 | I86: =N86 -> 185 | J86: Cước vận chuyển | L86: 46251 | M86: デビット ８１２０８０ | N86: 185 | P86: 4286458 | Q86: -
A87: Công ty | B87: =L87 -> 46251 | C87: =M87 -> 取消＊デビット １２４５５４ | E87: CTY | F87: 3m intel | G87: Khác | H87: =O87 -> 185 | I87: =N87 -> 0 | J87: Cước vận chuyển | L87: 46251 | M87: 取消＊デビット １２４５５４ | O87: 185 | P87: 4286643 | Q87: -
A88: Công ty | B88: =L88 -> 46251 | C88: =M88 -> デビット ８０５２０２ | E88: CTY | F88: 3m intel | G88: Khác | H88: =O88 -> 0 | I88: =N88 -> 185 | J88: Cước vận chuyển | L88: 46251 | M88: デビット ８０５２０２ | N88: 185 | P88: 4286458 | Q88: -
A89: Công ty | B89: =L89 -> 46251 | C89: =M89 -> デビット ８０４７３２ | E89: CTY | F89: 3m intel | G89: Khác | H89: =O89 -> 0 | I89: =N89 -> 185 | J89: Cước vận chuyển | L89: 46251 | M89: デビット ８０４７３２ | N89: 185 | P89: 4286643 | Q89: -
A90: Công ty | B90: =L90 -> 46251 | C90: =M90 -> デビット ８０３８４５ | E90: CTY | F90: 3m intel | G90: Khác | H90: =O90 -> 0 | I90: =N90 -> 185 | J90: Cước vận chuyển | L90: 46251 | M90: デビット ８０３８４５ | N90: 185 | P90: 4286828 | Q90: -
A91: Công ty | B91: =L91 -> 46251 | C91: =M91 -> デビット ８０３４２５ | E91: CTY | F91: 3m intel | G91: Khác | H91: =O91 -> 0 | I91: =N91 -> 185 | J91: Cước vận chuyển | L91: 46251 | M91: デビット ８０３４２５ | N91: 185 | P91: 4287013 | Q91: -
A92: Công ty | B92: =L92 -> 46251 | C92: =M92 -> デビット ８０２９９９ | E92: CTY | F92: 3m intel | G92: Khác | H92: =O92 -> 0 | I92: =N92 -> 185 | J92: Cước vận chuyển | L92: 46251 | M92: デビット ８０２９９９ | N92: 185 | P92: 4287198 | Q92: -
A93: Công ty | B93: =L93 -> 46251 | C93: =M93 -> デビット ７５０３４８ | E93: CTY | F93: 3m intel | G93: Khác | H93: =O93 -> 0 | I93: =N93 -> 185 | J93: Cước vận chuyển | L93: 46251 | M93: デビット ７５０３４８ | N93: 185 | P93: 4287383 | Q93: -
A94: Công ty | B94: =L94 -> 46251 | C94: =M94 -> デビット ７４９３２７ | E94: CTY | F94: 3m intel | G94: Khác | H94: =O94 -> 0 | I94: =N94 -> 185 | J94: Cước vận chuyển | L94: 46251 | M94: デビット ７４９３２７ | N94: 185 | P94: 4287568 | Q94: -
A95: Công ty | B95: =L95 -> 46251 | C95: =M95 -> デビット ７４８８３０ | E95: CTY | F95: 3m intel | G95: Khác | H95: =O95 -> 0 | I95: =N95 -> 185 | J95: Cước vận chuyển | L95: 46251 | M95: デビット ７４８８３０ | N95: 185 | P95: 4287753 | Q95: -
A96: Công ty | B96: =L96 -> 46251 | C96: =M96 -> デビット ７４８３４３ | E96: CTY | F96: 3m intel | G96: Khác | H96: =O96 -> 0 | I96: =N96 -> 185 | J96: Cước vận chuyển | L96: 46251 | M96: デビット ７４８３４３ | N96: 185 | P96: 4287938 | Q96: -
A97: Công ty | B97: =L97 -> 46251 | C97: =M97 -> デビット ７４８０１６ | E97: CTY | F97: 3m intel | G97: Khác | H97: =O97 -> 0 | I97: =N97 -> 185 | J97: Cước vận chuyển | L97: 46251 | M97: デビット ７４８０１６ | N97: 185 | P97: 4288123 | Q97: -
A98: Công ty | B98: =L98 -> 46251 | C98: =M98 -> 総合振込手数料 | E98: CTY | F98: 3m intel | G98: Khác | H98: =O98 -> 0 | I98: =N98 -> 2755 | J98: Phí chuyển khoản theo lô | L98: 46251 | M98: 総合振込手数料 | N98: 2755 | P98: 4288308 | Q98: -
A99: Công ty | B99: =L99 -> 46251 | C99: =M99 -> 振込＊ジーエムオーペイメントゲートウエイ | E99: CTY | F99: 3m intel | G99: Khác | H99: =O99 -> 2155162 | I99: =N99 -> 0 | J99: Luân chuyển từ GMO-> SBI | L99: 46251 | M99: 振込＊ジーエムオーペイメントゲートウエイ | O99: 2155162 | P99: 4291063 | Q99: -
A100: Công ty | B100: =L100 -> 46252 | C100: =M100 -> デビット ００４７６７ | E100: CTY | F100: 3m intel | G100: Khác | H100: =O100 -> 0 | I100: =N100 -> 185 | J100: Cước vận chuyển | L100: 46252 | M100: デビット ００４７６７ | N100: 185 | P100: 5789753 | Q100: -
A101: Công ty | B101: =L101 -> 46252 | C101: =M101 -> デビット ００４１３５ | E101: CTY | F101: 3m intel | G101: Khác | H101: =O101 -> 0 | I101: =N101 -> 185 | J101: Cước vận chuyển | L101: 46252 | M101: デビット ００４１３５ | N101: 185 | P101: 5789938 | Q101: -
A102: Công ty | B102: =L102 -> 46252 | C102: =M102 -> デビット ００２０５１ | E102: CTY | F102: 3m intel | G102: Khác | H102: =O102 -> 0 | I102: =N102 -> 185 | J102: Cước vận chuyển | L102: 46252 | M102: デビット ００２０５１ | N102: 185 | P102: 5790123 | Q102: -
A103: Công ty | B103: =L103 -> 46252 | C103: =M103 -> デビット ００１５６８ | E103: CTY | F103: 3m intel | G103: Khác | H103: =O103 -> 0 | I103: =N103 -> 185 | J103: Cước vận chuyển | L103: 46252 | M103: デビット ００１５６８ | N103: 185 | P103: 5790308 | Q103: -
A104: Công ty | B104: =L104 -> 46252 | C104: =M104 -> 振込＊ド ドウツク フイ | E104: KH01005 | F104: Huy Đỗ | G104: Cầm tay | H104: =O104 -> 3850 | I104: =N104 -> 0 | J104: Thu cước | L104: 46252 | M104: 振込＊ド ドウツク フイ | O104: 3850 | P104: 5790493 | Q104: -
A105: Công ty | B105: =L105 -> 46252 | C105: =M105 -> 振込＊アライ タカアキ | E105: CTY | F105: 3m intel | G105: Khác | H105: =O105 -> 1500000 | I105: =N105 -> 0 | J105: Luân chuyển từ Yucho-> SBI | L105: 46252 | M105: 振込＊アライ タカアキ | O105: 1500000 | P105: 5786643 | Q105: -
A106: Công ty | B106: =L106 -> 46253 | C106: =M106 -> 振込手数料 | E106: CTY | F106: 3m intel | G106: Khác | H106: =O106 -> 0 | I106: =N106 -> 140 | J106: Phí chuyển tiền | L106: 46253 | M106: 振込手数料 | N106: 140 | P106: 5043946 | Q106: -
A107: Công ty | B107: =L107 -> 46253 | C107: =M107 -> 振込＊ド）アシスト | E107: Assis | G107: Khác | H107: =O107 -> 0 | I107: =N107 -> 745667 | J107: Chuyển tiền chi Assis | L107: 46253 | M107: 振込＊ド）アシスト | N107: 745667 | P107: 5044086 | Q107: -
A108: Công ty | B108: =L108 -> 46254 | C108: =M108 -> デビット ６３６８６６ | E108: CTY | F108: 3m intel | G108: Khác | H108: =O108 -> 0 | I108: =N108 -> 600 | J108: Cước vận chuyển | L108: 46254 | M108: デビット ６３６８６６ | N108: 600 | P108: 4996036 | Q108: -
A109: Công ty | B109: =L109 -> 46254 | C109: =M109 -> 振込＊レー ヒユー デユイ | E109: KH01673 | F109: Alfred Herrera Espila | G109: Cầm tay | H109: =O109 -> 3850 | I109: =N109 -> 0 | J109: Thu cước | L109: 46254 | M109: 振込＊レー ヒユー デユイ | O109: 3850 | P109: 4996636 | Q109: -
A110: Công ty | B110: =L110 -> 46254 | C110: =M110 -> デビット ５２１９４７ | E110: CTY | F110: 3m intel | G110: Khác | H110: =O110 -> 0 | I110: =N110 -> 53900 | J110: Phí bảo hiểm Highmech | L110: 46254 | M110: デビット ５２１９４７ | N110: 53900 | P110: 4992786 | Q110: -
A111: Công ty | B111: =L111 -> 46254 | C111: =M111 -> 振込＊エスピラ アルフレド ヘーレラ | E111: KH00962 | F111: Hữu Duy | G111: Cầm tay | H111: =O111 -> 3850 | I111: =N111 -> 0 | J111: Thu cước | L111: 46254 | M111: 振込＊エスピラ アルフレド ヘーレラ | O111: 3850 | P111: 5046686 | Q111: -
A112: Công ty | B112: =L112 -> 46255 | C112: =M112 -> 振込＊オカダ エジバルド | E112: KH01182 | F112: Thanh Thanh | G112: Cầm tay | H112: =O112 -> 3850 | I112: =N112 -> 0 | J112: Thu cước | L112: 46255 | M112: 振込＊オカダ エジバルド | O112: 3850 | P112: 5002996 | Q112: -
A113: Công ty | B113: =L113 -> 46255 | C113: =M113 -> デビット ８８３６４９ | E113: CTY | F113: 3m intel | G113: Khác | H113: =O113 -> 0 | I113: =N113 -> 185 | J113: Cước vận chuyển | L113: 46255 | M113: デビット ８８３６４９ | N113: 185 | P113: 4999146 | Q113: -
A114: Công ty | B114: =L114 -> 46255 | C114: =M114 -> デビット ８８３１８７ | E114: CTY | F114: 3m intel | G114: Khác | H114: =O114 -> 0 | I114: =N114 -> 185 | J114: Cước vận chuyển | L114: 46255 | M114: デビット ８８３１８７ | N114: 185 | P114: 4999331 | Q114: -
A115: Công ty | B115: =L115 -> 46255 | C115: =M115 -> デビット ８８２５５２ | E115: CTY | F115: 3m intel | G115: Khác | H115: =O115 -> 0 | I115: =N115 -> 185 | J115: Cước vận chuyển | L115: 46255 | M115: デビット ８８２５５２ | N115: 185 | P115: 4999516 | Q115: -
A116: Công ty | B116: =L116 -> 46255 | C116: =M116 -> デビット ８８１４９２ | E116: CTY | F116: 3m intel | G116: Khác | H116: =O116 -> 0 | I116: =N116 -> 185 | J116: Cước vận chuyển | L116: 46255 | M116: デビット ８８１４９２ | N116: 185 | P116: 4999701 | Q116: -
A117: Công ty | B117: =L117 -> 46255 | C117: =M117 -> 振込＊デイン ウ゛ タイン ガン | E117: KH01323 | F117: Joao Meugmin | G117: Cầm tay | H117: =O117 -> 3850 | I117: =N117 -> 0 | J117: Thu cước | L117: 46255 | M117: 振込＊デイン ウ゛ タイン ガン | O117: 3850 | P117: 4999886 | Q117: -
...

Sheet Arai 7121
A1: NGÀY THÁNG | B1: THU | C1: CHI | E1: NỘI DUNG | G1: LOẠI DỊCH VỤ | H1: Mã U (NTT)
B2: =SUBTOTAL(9,B3:B1000) -> 973300 | C2: =SUBTOTAL(9,C3:C1000) -> 850000
A3: =I3 -> 20260801 | B3: =K3 -> 4000 | C3: =L3 -> 0 | D3: =M3 -> ことら | E3: =N3 -> ﾎｱﾝ ﾃｲ ﾎｱ | G3: Cố định | H3: U00007837117 | I3: 20260801 | J3: 202608010000001 | K3: 4000 | M3: ことら | N3: ﾎｱﾝ ﾃｲ ﾎｱ | O3: 301168
A4: =I4 -> 20260802 | B4: =K4 -> 4000 | C4: =L4 -> 0 | D4: =M4 -> 送金 | E4: =N4 -> ＲＡＪＡＰＡＫＳ | G4: Cố định | H4: U00007822655 | I4: 20260802 | J4: 202608020000001 | K4: 4000 | M4: 送金 | N4: ＲＡＪＡＰＡＫＳ | O4: 305168
A5: =I5 -> 20260803 | B5: =K5 -> 200000 | C5: =L5 -> 0 | D5: =M5 -> 振込 | E5: =N5 -> ｶ)ｼ-ｷﾔｽﾄ | G5: Khác | I5: 20260803 | J5: 202608030000001 | K5: 200000 | M5: 振込 | N5: ｶ)ｼ-ｷﾔｽﾄ | O5: 505168
A6: =I6 -> 20260804 | B6: =K6 -> 0 | C6: =L6 -> 200000 | D6: =M6 -> 通 帳 | E6: =N6 -> 0 | G6: Khác | I6: 20260804 | J6: 202608040000001 | L6: 200000 | M6: 通 帳 | O6: 305168
A7: =I7 -> 20260804 | B7: =K7 -> 1800 | C7: =L7 -> 0 | D7: =M7 -> 送金 | E7: =N7 -> ＮＧＵＹＥＮ Ｖ | G7: Cố định | H7: U00007825999 | I7: 20260804 | J7: 202608040000002 | K7: 1800 | M7: 送金 | N7: ＮＧＵＹＥＮ Ｖ | O7: 306968
A8: =I8 -> 20260805 | B8: =K8 -> 4000 | C8: =L8 -> 0 | D8: =M8 -> 送金 | E8: =N8 -> ＲＩＢＥＩＲＯ | G8: Cố định | H8: U00007819670 | I8: 20260805 | J8: 202608050000001 | K8: 4000 | M8: 送金 | N8: ＲＩＢＥＩＲＯ | O8: 310968
A9: =I9 -> 20260805 | B9: =K9 -> 2000 | C9: =L9 -> 0 | D9: =M9 -> 送金 | E9: =N9 -> ＴＡＫＥＩ ＣＯ | G9: Cố định | H9: U00007833901 | I9: 20260805 | J9: 202608050000002 | K9: 2000 | M9: 送金 | N9: ＴＡＫＥＩ ＣＯ | O9: 312968
A10: =I10 -> 20260806 | B10: =K10 -> 2000 | C10: =L10 -> 0 | D10: =M10 -> 送金 | E10: =N10 -> ＨＯＳＳＡＩＮ | G10: Cố định | H10: U00007829188 | I10: 20260806 | J10: 202608060000001 | K10: 2000 | M10: 送金 | N10: ＨＯＳＳＡＩＮ | O10: 314968
A11: =I11 -> 20260810 | B11: =K11 -> 4000 | C11: =L11 -> 0 | D11: =M11 -> 送金 | E11: =N11 -> ＭＵＮＡＭＢＡＭ | G11: Cố định | H11: U00007834092 | I11: 20260810 | J11: 202608100000001 | K11: 4000 | M11: 送金 | N11: ＭＵＮＡＭＢＡＭ | O11: 318968
A12: =I12 -> 20260823 | B12: =K12 -> 2000 | C12: =L12 -> 0 | D12: =M12 -> 送金 | E12: =N12 -> ＭＩＡ ＳＵＪＡ | G12: Cố định | H12: U00007836020 | I12: 20260823 | J12: 202608230000001 | K12: 2000 | M12: 送金 | N12: ＭＩＡ ＳＵＪＡ | O12: 320968
A13: =I13 -> 20260824 | B13: =K13 -> 2000 | C13: =L13 -> 0 | D13: =M13 -> 送金 | E13: =N13 -> ＮＥＰＡＬＩ Ｓ | G13: Cố định | H13: U00007766415 | I13: 20260824 | J13: 202608240000001 | K13: 2000 | M13: 送金 | N13: ＮＥＰＡＬＩ Ｓ | O13: 322968
A14: =I14 -> 20260824 | B14: =K14 -> 2000 | C14: =L14 -> 0 | D14: =M14 -> 送金 | E14: =N14 -> ＴＯＹＯＮＡＧＡ | G14: Cố định | H14: U00007842252 | I14: 20260824 | J14: 202608240000002 | K14: 2000 | M14: 送金 | N14: ＴＯＹＯＮＡＧＡ | O14: 324968
A15: =I15 -> 20260825 | B15: =K15 -> 1500 | C15: =L15 -> 0 | D15: =M15 -> 送金 | E15: =N15 -> ＴＯＹＯＤＡ Ｔ | G15: Cố định | H15: U00007833136 | I15: 20260825 | J15: 202608250000001 | K15: 1500 | M15: 送金 | N15: ＴＯＹＯＤＡ Ｔ | O15: 326468
A16: =I16 -> 20260826 | B16: =K16 -> 2000 | C16: =L16 -> 0 | D16: =M16 -> 送金 | E16: =N16 -> ＦＩＲＧＯ ＦＡ | G16: Cố định | H16: U00007821917 | I16: 20260826 | J16: 202608260000001 | K16: 2000 | M16: 送金 | N16: ＦＩＲＧＯ ＦＡ | O16: 328468
A17: =I17 -> 20260826 | B17: =K17 -> 500000 | C17: =L17 -> 0 | D17: =M17 -> 振込 | E17: =N17 -> ｶ)ｼ-ｷﾔｽﾄ | G17: Khác | I17: 20260826 | J17: 202608260000002 | K17: 500000 | M17: 振込 | N17: ｶ)ｼ-ｷﾔｽﾄ | O17: 828468
A18: =I18 -> 20260827 | B18: =K18 -> 0 | C18: =L18 -> 500000 | D18: =M18 -> 通 帳 | E18: =N18 -> 0 | G18: Khác | I18: 20260827 | J18: 202608270000001 | L18: 500000 | M18: 通 帳 | O18: 328468
A19: =I19 -> 20260827 | B19: =K19 -> 2000 | C19: =L19 -> 0 | D19: =M19 -> 送金 | E19: =N19 -> ＫＯＵＥＭＥＮＩ | G19: Cố định | H19: U00007874976 | I19: 20260827 | J19: 202608270000002 | K19: 2000 | M19: 送金 | N19: ＫＯＵＥＭＥＮＩ | O19: 330468
A20: =I20 -> 20260827 | B20: =K20 -> 4000 | C20: =L20 -> 0 | D20: =M20 -> 送金 | E20: =N20 -> ＰＨＡＮ ＴＨＩ | G20: Cố định | H20: U00007872512 | I20: 20260827 | J20: 202608270000003 | K20: 4000 | M20: 送金 | N20: ＰＨＡＮ ＴＨＩ | O20: 334468
A21: =I21 -> 20260827 | B21: =K21 -> 2000 | C21: =L21 -> 0 | D21: =M21 -> ことら | E21: =N21 -> ｸﾞｴﾝ ﾄﾞｳﾂｸ ﾄｳ | G21: Cố định | H21: U00007873626 | I21: 20260827 | J21: 202608270000004 | K21: 2000 | M21: ことら | N21: ｸﾞｴﾝ ﾄﾞｳﾂｸ ﾄｳ | O21: 336468
A22: =I22 -> 20260827 | B22: =K22 -> 2000 | C22: =L22 -> 0 | D22: =M22 -> 送金 | E22: =N22 -> ＶＵ ＭＡＮＨ | G22: Cố định | H22: U00007884054 | I22: 20260827 | J22: 202608270000005 | K22: 2000 | M22: 送金 | N22: ＶＵ ＭＡＮＨ | O22: 338468
A23: =I23 -> 20260827 | B23: =K23 -> 2000 | C23: =L23 -> 0 | D23: =M23 -> 送金 | E23: =N23 -> ＮＧＵＹＥＮ Ｖ | G23: Cố định | H23: U00007824109 | I23: 20260827 | J23: 202608270000006 | K23: 2000 | M23: 送金 | N23: ＮＧＵＹＥＮ Ｖ | O23: 340468
A24: =I24 -> 20260827 | B24: =K24 -> 3600 | C24: =L24 -> 0 | D24: =M24 -> 送金 | E24: =N24 -> ＮＧＵＹＥＮ Ｔ | G24: Cố định | H24: U00007850854 | I24: 20260827 | J24: 202608270000007 | K24: 3600 | M24: 送金 | N24: ＮＧＵＹＥＮ Ｔ | O24: 344068
A25: =I25 -> 20260828 | B25: =K25 -> 2000 | C25: =L25 -> 0 | D25: =M25 -> 送金 | E25: =N25 -> ＮＧＵＹＥＮ Ｈ | G25: Cố định | H25: U00007819941 | I25: 20260828 | J25: 202608280000001 | K25: 2000 | M25: 送金 | N25: ＮＧＵＹＥＮ Ｈ | O25: 346068 | P25: HD004318
A26: =I26 -> 20260828 | B26: =K26 -> 2000 | C26: =L26 -> 0 | D26: =M26 -> 振込 | E26: =N26 -> ｲｶﾞﾗｼｼﾞｴﾆﾌｱ- | G26: Cố định | H26: U00007835648 | I26: 20260828 | J26: 202608280000002 | K26: 2000 | M26: 振込 | N26: ｲｶﾞﾗｼｼﾞｴﾆﾌｱ- | O26: 348068
A27: =I27 -> 20260828 | B27: =K27 -> 2000 | C27: =L27 -> 0 | D27: =M27 -> 送金 | E27: =N27 -> ＳＹ ＴＨＩ Ｔ | G27: Cố định | H27: U00007839036 | I27: 20260828 | J27: 202608280000003 | K27: 2000 | M27: 送金 | N27: ＳＹ ＴＨＩ Ｔ | O27: 350068
A28: =I28 -> 20260828 | B28: =K28 -> 2000 | C28: =L28 -> 0 | D28: =M28 -> 送金 | E28: =N28 -> ｱﾗｲ ｷﾖｱｷ | G28: Cố định | H28: U00007835730 | I28: 20260828 | J28: 202608280000004 | K28: 2000 | M28: 送金 | N28: ｱﾗｲ ｷﾖｱｷ | O28: 352068
A29: =I29 -> 20260828 | B29: =K29 -> 2000 | C29: =L29 -> 0 | D29: =M29 -> 送金 | E29: =N29 -> ＮＧＵＹＥＮ Ｔ | G29: Cố định | H29: U00007805651 | I29: 20260828 | J29: 202608280000005 | K29: 2000 | M29: 送金 | N29: ＮＧＵＹＥＮ Ｔ | O29: 354068
A30: =I30 -> 20260828 | B30: =K30 -> 2000 | C30: =L30 -> 0 | D30: =M30 -> 送金 | E30: =N30 -> 大瀧 嘉賢 | G30: Cố định | H30: U00007861617 | I30: 20260828 | J30: 202608280000006 | K30: 2000 | M30: 送金 | N30: 大瀧 嘉賢 | O30: 356068
A31: =I31 -> 20260828 | B31: =K31 -> 2000 | C31: =L31 -> 0 | D31: =M31 -> 送金 | E31: =N31 -> ＳＵＹＡＬ ＧＡ | G31: Cố định | H31: U00007854447 | I31: 20260828 | J31: 202608280000007 | K31: 2000 | M31: 送金 | N31: ＳＵＹＡＬ ＧＡ | O31: 358068
A32: =I32 -> 20260828 | B32: =K32 -> 2000 | C32: =L32 -> 0 | D32: =M32 -> 送金 | E32: =N32 -> ＢＩＬＬＡＨ Ｍ | G32: Cố định | H32: U00007884015 | I32: 20260828 | J32: 202608280000008 | K32: 2000 | M32: 送金 | N32: ＢＩＬＬＡＨ Ｍ | O32: 360068
A33: =I33 -> 20260828 | B33: =K33 -> 2000 | C33: =L33 -> 0 | D33: =M33 -> 送金 | E33: =N33 -> ＴＡＫＡＨＡＳＨ | G33: Cố định | H33: U00007832610 | I33: 20260828 | J33: 202608280000009 | K33: 2000 | M33: 送金 | N33: ＴＡＫＡＨＡＳＨ | O33: 362068
A34: =I34 -> 20260828 | B34: =K34 -> 2000 | C34: =L34 -> 0 | D34: =M34 -> 送金 | E34: =N34 -> ＢＡＵＴＩＳＴＡ | G34: Cố định | H34: U00007807764 | I34: 20260828 | J34: 202608280000010 | K34: 2000 | M34: 送金 | N34: ＢＡＵＴＩＳＴＡ | O34: 364068
A35: =I35 -> 20260828 | B35: =K35 -> 2000 | C35: =L35 -> 0 | D35: =M35 -> 送金 | E35: =N35 -> ＶＵ ＴＵＮＧ | G35: Cố định | H35: U00007828034 | I35: 20260828 | J35: 202608280000011 | K35: 2000 | M35: 送金 | N35: ＶＵ ＴＵＮＧ | O35: 366068
A36: =I36 -> 20260828 | B36: =K36 -> 2000 | C36: =L36 -> 0 | D36: =M36 -> 送金 | E36: =N36 -> ＩＲＶＡＮ ＰＥ | G36: Cố định | H36: U00007777463 | I36: 20260828 | J36: 202608280000012 | K36: 2000 | M36: 送金 | N36: ＩＲＶＡＮ ＰＥ | O36: 368068
A37: =I37 -> 20260828 | B37: =K37 -> 2000 | C37: =L37 -> 0 | D37: =M37 -> 送金 | E37: =N37 -> 佐藤 由香里 | G37: Cố định | H37: U00007842185 | I37: 20260828 | J37: 202608280000013 | K37: 2000 | M37: 送金 | N37: 佐藤 由香里 | O37: 370068
... A47: =I47 -> 20260831 | B47: =K47 -> 2000 | C47: =L47 -> 0 | D47: =M47 -> 送金 | E47: =N47 -> ＳＡＮＴＯＳ Ｒ | G47: Cố định | H47: U00007787781 | I47: 20260831 | J47: 202608310000003 | K47: 2000 | M47: 送金 | N47: ＳＡＮＴＯＳ Ｒ | O47: 391068
A48: =I48 -> 20260831 | B48: =K48 -> 150000 | C48: =L48 -> 0 | D48: =M48 -> 振込 | E48: =N48 -> ｶ)ｼ-ｷﾔｽﾄ | G48: Khác | I48: 20260831 | J48: 202608310000004 | K48: 150000 | M48: 振込 | N48: ｶ)ｼ-ｷﾔｽﾄ | O48: 541068
A49: =I49 -> 20260831 | B49: =K49 -> 4000 | C49: =L49 -> 0 | D49: =M49 -> 送金 | E49: =N49 -> ＨＡＳＥＥＢ Ｍ | G49: Cố định | H49: U00007845671 | I49: 20260831 | J49: 202608310000005 | K49: 4000 | M49: 送金 | N49: ＨＡＳＥＥＢ Ｍ | O49: 545068
A50: =I50 -> 20260831 | B50: =K50 -> 2000 | C50: =L50 -> 0 | D50: =M50 -> 送金 | E50: =N50 -> ＧＥＮＯＮ ＲＯ | G50: Cố định | H50: U00007868236 | I50: 20260831 | J50: 202608310000006 | K50: 2000 | M50: 送金 | N50: ＧＥＮＯＮ ＲＯ | O50: 547068
A51: =I51 -> 20260831 | B51: =K51 -> 2000 | C51: =L51 -> 0 | D51: =M51 -> 送金 | E51: =N51 -> ｲｽﾙｱﾖﾏﾙ | G51: Cố định | H51: U00007835742 | I51: 20260831 | J51: 202608310000007 | K51: 2000 | M51: 送金 | N51: ｲｽﾙｱﾖﾏﾙ | O51: 549068
A52: =I52 -> 20260831 | B52: =K52 -> 2000 | C52: =L52 -> 0 | D52: =M52 -> 送金 | E52: =N52 -> ＨＡＧＩＨＡＲＡ | G52: Cố định | H52: U00007827399 | I52: 20260831 | J52: 202608310000008 | K52: 2000 | M52: 送金 | N52: ＨＡＧＩＨＡＲＡ | O52: 551068
A53: =I53 -> 20260831 | B53: =K53 -> 3000 | C53: =L53 -> 0 | D53: =M53 -> 送金 | E53: =N53 -> ＵＤＵＷＡＮＡＧ | G53: Cố định | H53: U00007855072 | I53: 20260831 | J53: 202608310000009 | K53: 3000 | M53: 送金 | N53: ＵＤＵＷＡＮＡＧ | O53: 554068
A54: =I54 -> 20260831 | B54: =K54 -> 0 | C54: =L54 -> 150000 | D54: =M54 -> 通 帳 | E54: =N54 -> 0 | G54: Khác | I54: 20260831 | J54: 202608310000010 | L54: 150000 | M54: 通 帳 | O54: 404068
A55: =I55 -> 20260831 | B55: =K55 -> 2600 | C55: =L55 -> 0 | D55: =M55 -> 送金 | E55: =N55 -> ＬＥ ＴＨＩ Ｔ | G55: Cố định | H55: U00007839293 | I55: 20260831 | J55: 202608310000011 | K55: 2600 | M55: 送金 | N55: ＬＥ ＴＨＩ Ｔ | O55: 406668
A56: =I56 -> 20260831 | B56: =K56 -> 2000 | C56: =L56 -> 0 | D56: =M56 -> 送金 | E56: =N56 -> ＫＡＭＳＡＬＩ | G56: Cố định | H56: U00007856210 | I56: 20260831 | J56: 202608310000012 | K56: 2000 | M56: 送金 | N56: ＫＡＭＳＡＬＩ | O56: 408668
A57: =I57 -> 20260831 | B57: =K57 -> 2000 | C57: =L57 -> 0 | D57: =M57 -> 送金 | E57: =N57 -> ＡＮＥＫＥ ＫＥ | G57: Cố định | H57: U00007852718 | I57: 20260831 | J57: 202608310000013 | K57: 2000 | M57: 送金 | N57: ＡＮＥＫＥ ＫＥ | O57: 410668
A58: =I58 -> 20260831 | B58: =K58 -> 2000 | C58: =L58 -> 0 | D58: =M58 -> 送金 | E58: =N58 -> ＴＵＯＮＧ ＴＨ | G58: Cố định | H58: U00007797888 | I58: 20260831 | J58: 202608310000014 | K58: 2000 | M58: 送金 | N58: ＴＵＯＮＧ ＴＨ | O58: 412668
A59: =I59 -> 20260831 | B59: =K59 -> 2000 | C59: =L59 -> 0 | D59: =M59 -> 振込 | E59: =N59 -> ﾊｶﾞ ﾁｱｷ | G59: Cố định | H59: U00007867634 | I59: 20260831 | J59: 202608310000015 | K59: 2000 | M59: 振込 | N59: ﾊｶﾞ ﾁｱｷ | O59: 414668
A60: =I60 -> 20260831 | B60: =K60 -> 2000 | C60: =L60 -> 0 | D60: =M60 -> 送金 | E60: =N60 -> ＲＥＺＡ ＭＡＨ | G60: Cố định | H60: U00007807872 | I60: 20260831 | J60: 202608310000016 | K60: 2000 | M60: 送金 | N60: ＲＥＺＡ ＭＡＨ | O60: 416668
A61: =I61 -> 20260831 | B61: =K61 -> 2000 | C61: =L61 -> 0 | D61: =M61 -> 送金 | E61: =N61 -> ＰＨＡＮ ＸＵＡ | G61: Cố định | H61: U00007873145 | I61: 20260831 | J61: 202608310000017 | K61: 2000 | M61: 送金 | N61: ＰＨＡＮ ＸＵＡ | O61: 418668
A62: =I62 -> 20260831 | B62: =K62 -> 1800 | C62: =L62 -> 0 | D62: =M62 -> 送金 | E62: =N62 -> ＢＵＩ ＴＨＩ | G62: Cố định | H62: U00007876813 | I62: 20260831 | J62: 202608310000018 | K62: 1800 | M62: 送金 | N62: ＢＵＩ ＴＨＩ | O62: 420468
